{
    "clone distribution": "alpha",
    "mbr_level": 7.0,
    "n_iterations": {
        "0": 12,
        "7.0": 4,
        "10": 1
    },
    "iterations": 20,
    "best_values": [
        1.7121547178722836,
        13.90689557301405,
        13.90689557301405,
        13.90689557301405,
        13.90689557301405,
        13.90689557301405,
        13.90689557301405,
        13.90689557301405,
        13.90689557301405,
        13.90689557301405,
        13.90689557301405,
        13.90689557301405,
        13.90689557301405,
        13.90689557301405,
        13.90689557301405,
        13.90689557301405,
        13.90689557301405,
        13.90689557301405,
        13.90689557301405,
        13.90689557301405,
        13.90689557301405
    ],
    "batches": [
        [
            [
                35.38155434472029,
                6.6865126514660655,
                0.0,
                50.0,
                0.0,
                0.0,
                11.0
            ],
            [
                35.38163866210716,
                6.686476309473461,
                0.0,
                50.0,
                0.0,
                0.0,
                6.0
            ],
            [
                35.38162557671565,
                6.686456156334033,
                0.0,
                50.0,
                0.0,
                0.0,
                16.0
            ],
            [
                35.3815964201673,
                6.6865399133792405,
                0.0,
                50.0,
                0.0,
                0.0,
                23.0
            ],
            [
                35.38161474015057,
                6.686465884594652,
                0.0,
                50.0,
                0.0,
                0.0,
                4.0
            ],
            [
                35.38154836608096,
                6.686491421453287,
                0.0,
                50.0,
                0.0,
                0.0,
                29.0
            ],
            [
                35.381582287567625,
                6.686503769679535,
                0.0,
                50.0,
                0.0,
                0.0,
                0.0
            ],
            [
                35.381562678801465,
                6.686525383438028,
                0.0,
                50.0,
                0.0,
                0.0,
                24.0
            ],
            [
                35.38157143602044,
                6.686521238658597,
                0.0,
                50.0,
                0.0,
                0.0,
                16.0
            ],
            [
                35.38159876840259,
                6.686442782932542,
                0.0,
                50.0,
                0.0,
                0.0,
                19.0
            ],
            [
                35.381624478824556,
                6.68648371952223,
                0.0,
                50.0,
                0.0,
                0.0,
                10.0
            ],
            [
                35.381576399949076,
                6.686501963424227,
                0.05379316908933161,
                23.174022482545684,
                26.772184348364984,
                7.0,
                18.0
            ]
        ],
        [
            [
                32.15700827030289,
                7.832151266912364,
                0.06210587196898875,
                7.887996337735089,
                13.140407668912921,
                10.0,
                14.0
            ]
        ],
        [
            [
                30.439732271219718,
                7.292237451610322,
                0.05625838524822228,
                2.6808408320256305,
                10.838723729983698,
                7.0,
                27.0
            ],
            [
                32.157418006951104,
                7.832016650457816,
                0.05637123378613444,
                4.387785408872283,
                11.036085869322605,
                7.0,
                27.0
            ],
            [
                33.52468075507734,
                6.953896245903408,
                0.009944306606198211,
                4.928910993135283,
                25.72460525455186,
                7.0,
                26.0
            ],
            [
                30.62115670172723,
                7.811069222327864,
                0.0005993249739391967,
                28.13892535358673,
                16.178314012302614,
                7.0,
                27.0
            ]
        ],
        [
            [
                34.0,
                6.8,
                0.0,
                50.0,
                0.0,
                0.0,
                20.0
            ],
            [
                34.0,
                6.8,
                0.0,
                50.0,
                0.0,
                0.0,
                19.0
            ],
            [
                34.0,
                6.8,
                0.0,
                50.0,
                0.0,
                0.0,
                7.0
            ],
            [
                34.0,
                6.8,
                0.0,
                50.0,
                0.0,
                0.0,
                12.0
            ],
            [
                34.0,
                6.8,
                0.0,
                50.0,
                0.0,
                0.0,
                16.0
            ],
            [
                34.0,
                6.8,
                0.0,
                50.0,
                0.0,
                0.0,
                4.0
            ],
            [
                34.0,
                6.8,
                0.0,
                50.0,
                0.0,
                0.0,
                7.0
            ],
            [
                34.0,
                6.8,
                0.0,
                50.0,
                0.0,
                0.0,
                26.0
            ],
            [
                34.0,
                6.8,
                0.0,
                50.0,
                0.0,
                0.0,
                23.0
            ],
            [
                34.0,
                6.8,
                0.0,
                50.0,
                0.0,
                0.0,
                13.0
            ],
            [
                34.0,
                6.8,
                0.0,
                50.0,
                0.0,
                0.0,
                0.0
            ],
            [
                34.0,
                6.8,
                0.0,
                50.0,
                0.0,
                0.0,
                29.0
            ]
        ],
        [
            [
                33.10562892673182,
                7.836163117576559,
                0.05097348041986685,
                0.0,
                8.793050230209793,
                7.0,
                26.0
            ],
            [
                31.70710136337692,
                7.177868119058919,
                0.01723308307115723,
                26.652411045525216,
                6.745905560580551,
                7.0,
                18.0
            ],
            [
                32.199971836055745,
                6.952712188086147,
                0.006935060135724262,
                2.5956286540201674,
                24.61204525874544,
                7.0,
                21.0
            ],
            [
                32.59210525060661,
                7.989999141991413,
                0.014344646612561195,
                0.8509574101365942,
                19.61452870787329,
                7.0,
                26.0
            ]
        ],
        [
            [
                32.74279455038485,
                6.9450093944946545,
                0.003178140637166587,
                0.0,
                23.967655138878786,
                7.0,
                26.0
            ],
            [
                32.199343243790025,
                7.988697744927869,
                0.014696846776670217,
                0.8990579467676199,
                19.50363462995824,
                7.0,
                28.0
            ],
            [
                32.166738497662784,
                8.0,
                0.008333045457247685,
                50.0,
                1.7763568394002505e-15,
                7.0,
                26.0
            ],
            [
                37.947124214636865,
                6.0,
                0.05744332058413551,
                0.0,
                3.5572008783160247,
                7.0,
                25.0
            ]
        ],
        [
            [
                30.0,
                6.0,
                0.0,
                50.0,
                0.0,
                0.0,
                4.0
            ],
            [
                30.0,
                6.0,
                0.0,
                50.0,
                0.0,
                0.0,
                24.0
            ],
            [
                30.0,
                6.0,
                0.0,
                50.0,
                0.0,
                0.0,
                11.0
            ],
            [
                30.0,
                6.0,
                0.0,
                50.0,
                0.0,
                0.0,
                6.0
            ],
            [
                30.0,
                6.0,
                0.0,
                50.0,
                0.0,
                0.0,
                13.0
            ],
            [
                30.0,
                6.0,
                0.0,
                50.0,
                0.0,
                0.0,
                27.0
            ],
            [
                30.0,
                6.0,
                0.0,
                50.0,
                0.0,
                0.0,
                15.0
            ],
            [
                30.0,
                6.0,
                0.0,
                50.0,
                0.0,
                0.0,
                25.0
            ],
            [
                30.0,
                6.0,
                0.0,
                50.0,
                0.0,
                0.0,
                7.0
            ],
            [
                30.0,
                6.0,
                0.0,
                50.0,
                0.0,
                0.0,
                20.0
            ],
            [
                30.0,
                6.0,
                0.0,
                50.0,
                0.0,
                0.0,
                17.0
            ],
            [
                30.0,
                6.0,
                0.0,
                50.0,
                0.0,
                0.0,
                1.0
            ]
        ],
        [
            [
                30.0,
                8.0,
                0.0,
                50.0,
                0.0,
                0.0,
                11.0
            ],
            [
                30.0,
                8.0,
                0.0,
                50.0,
                0.0,
                0.0,
                14.0
            ],
            [
                30.0,
                8.0,
                0.0,
                50.0,
                0.0,
                0.0,
                24.0
            ],
            [
                30.0,
                8.0,
                0.0,
                50.0,
                0.0,
                0.0,
                9.0
            ],
            [
                30.0,
                8.0,
                0.0,
                50.0,
                0.0,
                0.0,
                5.0
            ],
            [
                30.0,
                8.0,
                0.0,
                50.0,
                0.0,
                0.0,
                28.0
            ],
            [
                30.0,
                8.0,
                0.0,
                50.0,
                0.0,
                0.0,
                2.0
            ],
            [
                30.0,
                8.0,
                0.0,
                50.0,
                0.0,
                0.0,
                25.0
            ],
            [
                30.0,
                8.0,
                0.0,
                50.0,
                0.0,
                0.0,
                20.0
            ],
            [
                30.0,
                8.0,
                0.0,
                50.0,
                0.0,
                0.0,
                19.0
            ],
            [
                30.0,
                8.0,
                0.0,
                50.0,
                0.0,
                0.0,
                16.0
            ],
            [
                30.0,
                8.0,
                0.0,
                50.0,
                0.0,
                0.0,
                2.0
            ]
        ],
        [
            [
                40.0,
                6.0,
                0.0,
                50.0,
                0.0,
                0.0,
                18.0
            ],
            [
                40.0,
                6.0,
                0.0,
                50.0,
                0.0,
                0.0,
                12.0
            ],
            [
                40.0,
                6.0,
                0.0,
                50.0,
                0.0,
                0.0,
                22.0
            ],
            [
                40.0,
                6.0,
                0.0,
                50.0,
                0.0,
                0.0,
                4.0
            ],
            [
                40.0,
                6.0,
                0.0,
                50.0,
                0.0,
                0.0,
                26.0
            ],
            [
                40.0,
                6.0,
                0.0,
                50.0,
                0.0,
                0.0,
                27.0
            ],
            [
                40.0,
                6.0,
                0.0,
                50.0,
                0.0,
                0.0,
                23.0
            ],
            [
                40.0,
                6.0,
                0.0,
                50.0,
                0.0,
                0.0,
                7.0
            ],
            [
                40.0,
                6.0,
                0.0,
                50.0,
                0.0,
                0.0,
                12.0
            ],
            [
                40.0,
                6.0,
                0.0,
                50.0,
                0.0,
                0.0,
                1.0
            ],
            [
                40.0,
                6.0,
                0.0,
                50.0,
                0.0,
                0.0,
                8.0
            ],
            [
                40.0,
                6.0,
                0.0,
                50.0,
                0.0,
                0.0,
                17.0
            ]
        ],
        [
            [
                30.0,
                6.0,
                0.0,
                50.0,
                0.0,
                0.0,
                8.0
            ],
            [
                30.0,
                6.0,
                0.0,
                50.0,
                0.0,
                0.0,
                4.0
            ],
            [
                30.0,
                6.0,
                0.0,
                50.0,
                0.0,
                0.0,
                5.0
            ],
            [
                30.0,
                6.0,
                0.0,
                50.0,
                0.0,
                0.0,
                18.0
            ],
            [
                30.0,
                6.0,
                0.0,
                50.0,
                0.0,
                0.0,
                20.0
            ],
            [
                30.0,
                6.0,
                0.0,
                50.0,
                0.0,
                0.0,
                14.0
            ],
            [
                30.0,
                6.0,
                0.0,
                50.0,
                0.0,
                0.0,
                27.0
            ],
            [
                30.0,
                6.0,
                0.0,
                50.0,
                0.0,
                0.0,
                10.0
            ],
            [
                30.0,
                6.0,
                0.0,
                50.0,
                0.0,
                0.0,
                2.0
            ],
            [
                30.0,
                6.0,
                0.0,
                50.0,
                0.0,
                0.0,
                25.0
            ],
            [
                30.0,
                6.0,
                0.0,
                50.0,
                0.0,
                0.0,
                16.0
            ],
            [
                30.0,
                6.0,
                0.0,
                50.0,
                0.0,
                0.0,
                22.0
            ]
        ],
        [
            [
                33.55197583516837,
                6.636161811505001,
                0.008698624590237798,
                1.3429257705865894e-12,
                20.372031136439816,
                7.0,
                19.0
            ],
            [
                31.622453332409826,
                7.639200949499586,
                0.0327739302189497,
                0.27698800518145106,
                9.226331718208868,
                7.0,
                19.0
            ],
            [
                31.471739661368836,
                7.380081986422224,
                0.031301243373060554,
                15.37242074369588,
                1.5531845382867802,
                7.0,
                26.0
            ],
            [
                30.86521156053284,
                7.920551466890556,
                0.05073523187872062,
                0.0,
                1.5095793770033175,
                7.0,
                26.0
            ]
        ],
        [
            [
                37.341094019212704,
                6.000000000000903,
                0.0,
                11.10259412569346,
                19.0345399648334,
                7.0,
                26.0
            ],
            [
                31.842832800786784,
                7.284021282887241,
                0.010448848360611529,
                29.589708008384132,
                7.453315819084356,
                7.0,
                25.0
            ],
            [
                30.127943610641715,
                7.719534055511712,
                0.022818815153954945,
                13.847327627109745,
                7.264488974230021,
                7.0,
                22.0
            ],
            [
                39.999999999999986,
                7.622242078632109,
                0.02489874970605863,
                3.4925588068022364,
                8.551437887056931,
                7.0,
                25.0
            ]
        ],
        [
            [
                39.999999999999986,
                8.0,
                0.04690257091434534,
                7.105427357601002e-15,
                0.0,
                10.0,
                14.0
            ]
        ],
        [
            [
                30.0,
                6.0,
                0.0,
                50.0,
                0.0,
                0.0,
                13.0
            ],
            [
                30.0,
                6.0,
                0.0,
                50.0,
                0.0,
                0.0,
                8.0
            ],
            [
                30.0,
                6.0,
                0.0,
                50.0,
                0.0,
                0.0,
                17.0
            ],
            [
                30.0,
                6.0,
                0.0,
                50.0,
                0.0,
                0.0,
                27.0
            ],
            [
                30.0,
                6.0,
                0.0,
                50.0,
                0.0,
                0.0,
                24.0
            ],
            [
                30.0,
                6.0,
                0.0,
                50.0,
                0.0,
                0.0,
                21.0
            ],
            [
                30.0,
                6.0,
                0.0,
                50.0,
                0.0,
                0.0,
                18.0
            ],
            [
                30.0,
                6.0,
                0.0,
                50.0,
                0.0,
                0.0,
                3.0
            ],
            [
                30.0,
                6.0,
                0.0,
                50.0,
                0.0,
                0.0,
                29.0
            ],
            [
                30.0,
                6.0,
                0.0,
                50.0,
                0.0,
                0.0,
                5.0
            ],
            [
                30.0,
                6.0,
                0.0,
                50.0,
                0.0,
                0.0,
                1.0
            ],
            [
                30.0,
                6.0,
                0.0,
                50.0,
                0.0,
                0.0,
                10.0
            ]
        ],
        [
            [
                30.0,
                6.0,
                0.0,
                50.0,
                0.0,
                0.0,
                23.0
            ],
            [
                30.0,
                6.0,
                0.0,
                50.0,
                0.0,
                0.0,
                0.0
            ],
            [
                30.0,
                6.0,
                0.0,
                50.0,
                0.0,
                0.0,
                27.0
            ],
            [
                30.0,
                6.0,
                0.0,
                50.0,
                0.0,
                0.0,
                5.0
            ],
            [
                30.0,
                6.0,
                0.0,
                50.0,
                0.0,
                0.0,
                20.0
            ],
            [
                30.0,
                6.0,
                0.0,
                50.0,
                0.0,
                0.0,
                11.0
            ],
            [
                30.0,
                6.0,
                0.0,
                50.0,
                0.0,
                0.0,
                16.0
            ],
            [
                30.0,
                6.0,
                0.0,
                50.0,
                0.0,
                0.0,
                2.0
            ],
            [
                30.0,
                6.0,
                0.0,
                50.0,
                0.0,
                0.0,
                8.0
            ],
            [
                30.0,
                6.0,
                0.0,
                50.0,
                0.0,
                0.0,
                13.0
            ],
            [
                30.0,
                6.0,
                0.0,
                50.0,
                0.0,
                0.0,
                28.0
            ],
            [
                30.0,
                6.0,
                0.0,
                50.0,
                0.0,
                0.0,
                19.0
            ]
        ],
        [
            [
                30.0,
                6.0,
                0.0,
                50.0,
                0.0,
                0.0,
                24.0
            ],
            [
                30.0,
                6.0,
                0.0,
                50.0,
                0.0,
                0.0,
                6.0
            ],
            [
                30.0,
                6.0,
                0.0,
                50.0,
                0.0,
                0.0,
                12.0
            ],
            [
                30.0,
                6.0,
                0.0,
                50.0,
                0.0,
                0.0,
                13.0
            ],
            [
                30.0,
                6.0,
                0.0,
                50.0,
                0.0,
                0.0,
                4.0
            ],
            [
                30.0,
                6.0,
                0.0,
                50.0,
                0.0,
                0.0,
                1.0
            ],
            [
                30.0,
                6.0,
                0.0,
                50.0,
                0.0,
                0.0,
                16.0
            ],
            [
                30.0,
                6.0,
                0.0,
                50.0,
                0.0,
                0.0,
                25.0
            ],
            [
                30.0,
                6.0,
                0.0,
                50.0,
                0.0,
                0.0,
                21.0
            ],
            [
                30.0,
                6.0,
                0.0,
                50.0,
                0.0,
                0.0,
                18.0
            ],
            [
                30.0,
                6.0,
                0.0,
                50.0,
                0.0,
                0.0,
                28.0
            ],
            [
                30.0,
                6.0,
                0.0,
                50.0,
                0.0,
                0.0,
                8.0
            ]
        ],
        [
            [
                30.0,
                6.0,
                0.0,
                50.0,
                0.0,
                0.0,
                6.0
            ],
            [
                30.0,
                6.0,
                0.0,
                50.0,
                0.0,
                0.0,
                1.0
            ],
            [
                30.0,
                6.0,
                0.0,
                50.0,
                0.0,
                0.0,
                21.0
            ],
            [
                30.0,
                6.0,
                0.0,
                50.0,
                0.0,
                0.0,
                27.0
            ],
            [
                30.0,
                6.0,
                0.0,
                50.0,
                0.0,
                0.0,
                28.0
            ],
            [
                30.0,
                6.0,
                0.0,
                50.0,
                0.0,
                0.0,
                13.0
            ],
            [
                30.0,
                6.0,
                0.0,
                50.0,
                0.0,
                0.0,
                4.0
            ],
            [
                30.0,
                6.0,
                0.0,
                50.0,
                0.0,
                0.0,
                18.0
            ],
            [
                30.0,
                6.0,
                0.0,
                50.0,
                0.0,
                0.0,
                22.0
            ],
            [
                30.0,
                6.0,
                0.0,
                50.0,
                0.0,
                0.0,
                8.0
            ],
            [
                30.0,
                6.0,
                0.0,
                50.0,
                0.0,
                0.0,
                16.0
            ],
            [
                30.0,
                6.0,
                0.0,
                50.0,
                0.0,
                0.0,
                11.0
            ]
        ],
        [
            [
                30.0,
                6.0,
                0.0,
                50.0,
                0.0,
                0.0,
                21.0
            ],
            [
                30.0,
                6.0,
                0.0,
                50.0,
                0.0,
                0.0,
                8.0
            ],
            [
                30.0,
                6.0,
                0.0,
                50.0,
                0.0,
                0.0,
                14.0
            ],
            [
                30.0,
                6.0,
                0.0,
                50.0,
                0.0,
                0.0,
                4.0
            ],
            [
                30.0,
                6.0,
                0.0,
                50.0,
                0.0,
                0.0,
                1.0
            ],
            [
                30.0,
                6.0,
                0.0,
                50.0,
                0.0,
                0.0,
                15.0
            ],
            [
                30.0,
                6.0,
                0.0,
                50.0,
                0.0,
                0.0,
                22.0
            ],
            [
                30.0,
                6.0,
                0.0,
                50.0,
                0.0,
                0.0,
                7.0
            ],
            [
                30.0,
                6.0,
                0.0,
                50.0,
                0.0,
                0.0,
                26.0
            ],
            [
                30.0,
                6.0,
                0.0,
                50.0,
                0.0,
                0.0,
                29.0
            ],
            [
                30.0,
                6.0,
                0.0,
                50.0,
                0.0,
                0.0,
                10.0
            ],
            [
                30.0,
                6.0,
                0.0,
                50.0,
                0.0,
                0.0,
                17.0
            ]
        ],
        [
            [
                30.0,
                6.0,
                0.0,
                50.0,
                0.0,
                0.0,
                16.0
            ],
            [
                30.0,
                6.0,
                0.0,
                50.0,
                0.0,
                0.0,
                23.0
            ],
            [
                30.0,
                6.0,
                0.0,
                50.0,
                0.0,
                0.0,
                25.0
            ],
            [
                30.0,
                6.0,
                0.0,
                50.0,
                0.0,
                0.0,
                13.0
            ],
            [
                30.0,
                6.0,
                0.0,
                50.0,
                0.0,
                0.0,
                2.0
            ],
            [
                30.0,
                6.0,
                0.0,
                50.0,
                0.0,
                0.0,
                7.0
            ],
            [
                30.0,
                6.0,
                0.0,
                50.0,
                0.0,
                0.0,
                5.0
            ],
            [
                30.0,
                6.0,
                0.0,
                50.0,
                0.0,
                0.0,
                10.0
            ],
            [
                30.0,
                6.0,
                0.0,
                50.0,
                0.0,
                0.0,
                22.0
            ],
            [
                30.0,
                6.0,
                0.0,
                50.0,
                0.0,
                0.0,
                1.0
            ],
            [
                30.0,
                6.0,
                0.0,
                50.0,
                0.0,
                0.0,
                29.0
            ],
            [
                30.0,
                6.0,
                0.0,
                50.0,
                0.0,
                0.0,
                19.0
            ]
        ],
        [
            [
                30.0,
                6.0,
                -4.336808689942018e-19,
                50.0,
                -2.220446049250313e-16,
                0.0,
                11.0
            ],
            [
                30.0,
                6.0,
                -4.336808689942018e-19,
                50.0,
                -2.220446049250313e-16,
                0.0,
                0.0
            ],
            [
                30.0,
                6.0,
                -4.336808689942018e-19,
                50.0,
                -2.220446049250313e-16,
                0.0,
                22.0
            ],
            [
                30.0,
                6.0,
                -4.336808689942018e-19,
                50.0,
                -2.220446049250313e-16,
                0.0,
                27.0
            ],
            [
                30.0,
                6.0,
                -4.336808689942018e-19,
                50.0,
                -2.220446049250313e-16,
                0.0,
                3.0
            ],
            [
                30.0,
                6.0,
                -4.336808689942018e-19,
                50.0,
                -2.220446049250313e-16,
                0.0,
                12.0
            ],
            [
                30.0,
                6.0,
                -4.336808689942018e-19,
                50.0,
                -2.220446049250313e-16,
                0.0,
                21.0
            ],
            [
                30.0,
                6.0,
                -4.336808689942018e-19,
                50.0,
                -2.220446049250313e-16,
                0.0,
                16.0
            ],
            [
                30.0,
                6.0,
                -4.336808689942018e-19,
                50.0,
                -2.220446049250313e-16,
                0.0,
                7.0
            ],
            [
                30.0,
                6.0,
                -4.336808689942018e-19,
                50.0,
                -2.220446049250313e-16,
                0.0,
                28.0
            ],
            [
                30.0,
                6.0,
                -4.336808689942018e-19,
                50.0,
                -2.220446049250313e-16,
                0.0,
                8.0
            ],
            [
                30.0,
                6.0,
                -4.336808689942018e-19,
                50.0,
                -2.220446049250313e-16,
                0.0,
                19.0
            ]
        ],
        [
            [
                30.0,
                6.0,
                0.00099629417739558,
                50.0,
                0.0,
                10.0,
                25.0
            ]
        ]
    ],
    "best_points": [
        [
            35.38161474015057,
            6.686465884594652,
            0.0,
            50.0,
            0.0,
            0.0,
            4.0
        ],
        [
            32.15700827030289,
            7.832151266912364,
            0.06210587196898875,
            7.887996337735089,
            13.140407668912921,
            10.0,
            14.0
        ],
        [
            33.52468075507734,
            6.953896245903408,
            0.009944306606198211,
            4.928910993135283,
            25.72460525455186,
            7.0,
            26.0
        ],
        [
            34.0,
            6.8,
            0.0,
            50.0,
            0.0,
            0.0,
            4.0
        ],
        [
            33.10562892673182,
            7.836163117576559,
            0.05097348041986685,
            0.0,
            8.793050230209793,
            7.0,
            26.0
        ],
        [
            37.947124214636865,
            6.0,
            0.05744332058413551,
            0.0,
            3.5572008783160247,
            7.0,
            25.0
        ],
        [
            30.0,
            6.0,
            0.0,
            50.0,
            0.0,
            0.0,
            4.0
        ],
        [
            30.0,
            8.0,
            0.0,
            50.0,
            0.0,
            0.0,
            25.0
        ],
        [
            40.0,
            6.0,
            0.0,
            50.0,
            0.0,
            0.0,
            4.0
        ],
        [
            30.0,
            6.0,
            0.0,
            50.0,
            0.0,
            0.0,
            25.0
        ],
        [
            31.471739661368836,
            7.380081986422224,
            0.031301243373060554,
            15.37242074369588,
            1.5531845382867802,
            7.0,
            26.0
        ],
        [
            31.842832800786784,
            7.284021282887241,
            0.010448848360611529,
            29.589708008384132,
            7.453315819084356,
            7.0,
            25.0
        ],
        [
            39.999999999999986,
            8.0,
            0.04690257091434534,
            7.105427357601002e-15,
            0.0,
            10.0,
            14.0
        ],
        [
            30.0,
            6.0,
            0.0,
            50.0,
            0.0,
            0.0,
            3.0
        ],
        [
            30.0,
            6.0,
            0.0,
            50.0,
            0.0,
            0.0,
            27.0
        ],
        [
            30.0,
            6.0,
            0.0,
            50.0,
            0.0,
            0.0,
            6.0
        ],
        [
            30.0,
            6.0,
            0.0,
            50.0,
            0.0,
            0.0,
            4.0
        ],
        [
            30.0,
            6.0,
            0.0,
            50.0,
            0.0,
            0.0,
            4.0
        ],
        [
            30.0,
            6.0,
            0.0,
            50.0,
            0.0,
            0.0,
            25.0
        ],
        [
            30.0,
            6.0,
            -4.336808689942018e-19,
            50.0,
            -2.220446049250313e-16,
            0.0,
            3.0
        ],
        [
            30.0,
            6.0,
            0.00099629417739558,
            50.0,
            0.0,
            10.0,
            25.0
        ]
    ],
    "cumulative_cost_list": [
        0,
        120,
        2220,
        4520,
        4640,
        6940,
        9240,
        9360,
        9480,
        9600,
        9720,
        12020,
        14320,
        16420,
        16540,
        16660,
        16780,
        16900,
        17020,
        17140,
        17260,
        19360
    ],
    "fidelities": [
        0,
        10,
        7.0,
        0,
        7.0,
        7.0,
        0,
        0,
        0,
        0,
        7.0,
        7.0,
        10,
        0,
        0,
        0,
        0,
        0,
        0,
        0,
        10
    ],
    "Xtrain": [
        [
            1.2229102392097488,
            0.41258431110141536,
            -0.298698352180609,
            0.36283058476966806,
            -0.3103400041677401,
            -0.38944672083111465,
            11.0
        ],
        [
            1.2229381904048753,
            0.4125308823859488,
            -0.298698352180609,
            0.36283058476966806,
            -0.3103400041677401,
            -0.38944672083111465,
            6.0
        ],
        [
            1.2229338526004798,
            0.412501253951317,
            -0.298698352180609,
            0.36283058476966806,
            -0.3103400041677401,
            -0.38944672083111465,
            16.0
        ],
        [
            1.22292418721114,
            0.4126243906044284,
            -0.298698352180609,
            0.36283058476966806,
            -0.3103400041677401,
            -0.38944672083111465,
            23.0
        ],
        [
            1.2229302602815482,
            0.4125155560968891,
            -0.298698352180609,
            0.36283058476966806,
            -0.3103400041677401,
            -0.38944672083111465,
            4.0
        ],
        [
            1.2229082572921313,
            0.4125530994855732,
            -0.298698352180609,
            0.36283058476966806,
            -0.3103400041677401,
            -0.38944672083111465,
            29.0
        ],
        [
            1.222919502257469,
            0.4125712534121873,
            -0.298698352180609,
            0.36283058476966806,
            -0.3103400041677401,
            -0.38944672083111465,
            0.0
        ],
        [
            1.2229130019558172,
            0.4126030291974397,
            -0.298698352180609,
            0.36283058476966806,
            -0.3103400041677401,
            -0.38944672083111465,
            24.0
        ],
        [
            1.2229159049719724,
            0.41259693568893874,
            -0.298698352180609,
            0.36283058476966806,
            -0.3103400041677401,
            -0.38944672083111465,
            16.0
        ],
        [
            1.2229249656506207,
            0.4124815928482285,
            -0.298698352180609,
            0.36283058476966806,
            -0.3103400041677401,
            -0.38944672083111465,
            19.0
        ],
        [
            1.2229334886498249,
            0.41254177637824013,
            -0.298698352180609,
            0.36283058476966806,
            -0.3103400041677401,
            -0.38944672083111465,
            10.0
        ],
        [
            1.22291755051322,
            0.41256859791935396,
            4.1828073259594545,
            -1.522481405261219,
            4.899755594049796,
            2.367484020419657,
            18.0
        ],
        [
            0.1539739275878453,
            2.0968617880720095,
            4.875338102385915,
            -2.5967732312342333,
            2.2468954930832825,
            3.5490257666699883,
            14.0
        ],
        [
            -0.4153026868976345,
            1.3030995437151918,
            4.388184335734887,
            -2.9627286825307197,
            1.798968151680693,
            2.367484020419657,
            27.0
        ],
        [
            0.15410975519625034,
            2.096663879709488,
            4.397585740634146,
            -2.8427657445556425,
            1.8373765086546443,
            2.367484020419657,
            27.0
        ],
        [
            0.6073570542797802,
            0.805682238973563,
            0.5297612324710295,
            -2.804735795732353,
            4.695887760389305,
            2.367484020419657,
            26.0
        ],
        [
            -0.3551605282467171,
            2.065867709849245,
            -0.24876862468492356,
            -1.173551309199589,
            2.8380979986964787,
            2.367484020419657,
            27.0
        ],
        [
            0.7649252790111739,
            0.5794294073470186,
            -0.298698352180609,
            0.36283058476966806,
            -0.3103400041677401,
            -0.38944672083111465,
            20.0
        ],
        [
            0.7649252790111739,
            0.5794294073470186,
            -0.298698352180609,
            0.36283058476966806,
            -0.3103400041677401,
            -0.38944672083111465,
            19.0
        ],
        [
            0.7649252790111739,
            0.5794294073470186,
            -0.298698352180609,
            0.36283058476966806,
            -0.3103400041677401,
            -0.38944672083111465,
            7.0
        ],
        [
            0.7649252790111739,
            0.5794294073470186,
            -0.298698352180609,
            0.36283058476966806,
            -0.3103400041677401,
            -0.38944672083111465,
            12.0
        ],
        [
            0.7649252790111739,
            0.5794294073470186,
            -0.298698352180609,
            0.36283058476966806,
            -0.3103400041677401,
            -0.38944672083111465,
            16.0
        ],
        [
            0.7649252790111739,
            0.5794294073470186,
            -0.298698352180609,
            0.36283058476966806,
            -0.3103400041677401,
            -0.38944672083111465,
            4.0
        ],
        [
            0.7649252790111739,
            0.5794294073470186,
            -0.298698352180609,
            0.36283058476966806,
            -0.3103400041677401,
            -0.38944672083111465,
            7.0
        ],
        [
            0.7649252790111739,
            0.5794294073470186,
            -0.298698352180609,
            0.36283058476966806,
            -0.3103400041677401,
            -0.38944672083111465,
            26.0
        ],
        [
            0.7649252790111739,
            0.5794294073470186,
            -0.298698352180609,
            0.36283058476966806,
            -0.3103400041677401,
            -0.38944672083111465,
            23.0
        ],
        [
            0.7649252790111739,
            0.5794294073470186,
            -0.298698352180609,
            0.36283058476966806,
            -0.3103400041677401,
            -0.38944672083111465,
            13.0
        ],
        [
            0.7649252790111739,
            0.5794294073470186,
            -0.298698352180609,
            0.36283058476966806,
            -0.3103400041677401,
            -0.38944672083111465,
            0.0
        ],
        [
            0.7649252790111739,
            0.5794294073470186,
            -0.298698352180609,
            0.36283058476966806,
            -0.3103400041677401,
            -0.38944672083111465,
            29.0
        ],
        [
            0.46844146571868,
            2.102759869389774,
            3.9478992326696014,
            -3.151136406375779,
            1.400862627010899,
            2.367484020419657,
            26.0
        ],
        [
            0.004829887290776972,
            1.1349577856814461,
            1.136988760935896,
            -1.2780225534074605,
            1.0024708001295344,
            2.367484020419657,
            18.0
        ],
        [
            0.16821634014765996,
            0.8039414789414235,
            0.279061090191691,
            -2.9687173381458156,
            4.479374088532046,
            2.367484020419657,
            21.0
        ],
        [
            0.2982084804799809,
            2.32892416550832,
            0.8963532934725728,
            -3.091331681373967,
            3.506814709554498,
            2.367484020419657,
            26.0
        ],
        [
            0.3481619500811076,
            0.7926171035398055,
            -0.033927647042613786,
            -3.151136406375779,
            4.353970270772321,
            2.367484020419657,
            26.0
        ],
        [
            0.1680079619503802,
            2.32701089745575,
            0.9256950679397973,
            -3.0879512074144104,
            3.485233775414214,
            2.367484020419657,
            28.0
        ],
        [
            0.1571994958090122,
            2.343627074145597,
            0.3955271631601673,
            0.36283058476966806,
            -0.31034000416773977,
            2.367484020419657,
            26.0
        ],
        [
            2.0733960845554065,
            -0.5967023705186999,
            4.486901227229147,
            -3.151136406375779,
            0.3819216505754872,
            2.367484020419657,
            25.0
        ],
        [
            -0.5610738377048543,
            -0.5967023705186999,
            -0.298698352180609,
            0.36283058476966806,
            -0.3103400041677401,
            -0.38944672083111465,
            4.0
        ],
        [
            -0.5610738377048543,
            -0.5967023705186999,
            -0.298698352180609,
            0.36283058476966806,
            -0.3103400041677401,
            -0.38944672083111465,
            24.0
        ],
        [
            -0.5610738377048543,
            -0.5967023705186999,
            -0.298698352180609,
            0.36283058476966806,
            -0.3103400041677401,
            -0.38944672083111465,
            11.0
        ],
        [
            -0.5610738377048543,
            -0.5967023705186999,
            -0.298698352180609,
            0.36283058476966806,
            -0.3103400041677401,
            -0.38944672083111465,
            6.0
        ],
        [
            -0.5610738377048543,
            -0.5967023705186999,
            -0.298698352180609,
            0.36283058476966806,
            -0.3103400041677401,
            -0.38944672083111465,
            13.0
        ],
        [
            -0.5610738377048543,
            -0.5967023705186999,
            -0.298698352180609,
            0.36283058476966806,
            -0.3103400041677401,
            -0.38944672083111465,
            27.0
        ],
        [
            -0.5610738377048543,
            -0.5967023705186999,
            -0.298698352180609,
            0.36283058476966806,
            -0.3103400041677401,
            -0.38944672083111465,
            15.0
        ],
        [
            -0.5610738377048543,
            -0.5967023705186999,
            -0.298698352180609,
            0.36283058476966806,
            -0.3103400041677401,
            -0.38944672083111465,
            25.0
        ],
        [
            -0.5610738377048543,
            -0.5967023705186999,
            -0.298698352180609,
            0.36283058476966806,
            -0.3103400041677401,
            -0.38944672083111465,
            7.0
        ],
        [
            -0.5610738377048543,
            -0.5967023705186999,
            -0.298698352180609,
            0.36283058476966806,
            -0.3103400041677401,
            -0.38944672083111465,
            20.0
        ],
        [
            -0.5610738377048543,
            -0.5967023705186999,
            -0.298698352180609,
            0.36283058476966806,
            -0.3103400041677401,
            -0.38944672083111465,
            17.0
        ],
        [
            -0.5610738377048543,
            -0.5967023705186999,
            -0.298698352180609,
            0.36283058476966806,
            -0.3103400041677401,
            -0.38944672083111465,
            1.0
        ],
        [
            -0.5610738377048543,
            2.343627074145597,
            -0.298698352180609,
            0.36283058476966806,
            -0.3103400041677401,
            -0.38944672083111465,
            11.0
        ],
        [
            -0.5610738377048543,
            2.343627074145597,
            -0.298698352180609,
            0.36283058476966806,
            -0.3103400041677401,
            -0.38944672083111465,
            14.0
        ],
        [
            -0.5610738377048543,
            2.343627074145597,
            -0.298698352180609,
            0.36283058476966806,
            -0.3103400041677401,
            -0.38944672083111465,
            24.0
        ],
        [
            -0.5610738377048543,
            2.343627074145597,
            -0.298698352180609,
            0.36283058476966806,
            -0.3103400041677401,
            -0.38944672083111465,
            9.0
        ],
        [
            -0.5610738377048543,
            2.343627074145597,
            -0.298698352180609,
            0.36283058476966806,
            -0.3103400041677401,
            -0.38944672083111465,
            5.0
        ],
        [
            -0.5610738377048543,
            2.343627074145597,
            -0.298698352180609,
            0.36283058476966806,
            -0.3103400041677401,
            -0.38944672083111465,
            28.0
        ],
        [
            -0.5610738377048543,
            2.343627074145597,
            -0.298698352180609,
            0.36283058476966806,
            -0.3103400041677401,
            -0.38944672083111465,
            2.0
        ],
        [
            -0.5610738377048543,
            2.343627074145597,
            -0.298698352180609,
            0.36283058476966806,
            -0.3103400041677401,
            -0.38944672083111465,
            25.0
        ],
        [
            -0.5610738377048543,
            2.343627074145597,
            -0.298698352180609,
            0.36283058476966806,
            -0.3103400041677401,
            -0.38944672083111465,
            20.0
        ],
        [
            -0.5610738377048543,
            2.343627074145597,
            -0.298698352180609,
            0.36283058476966806,
            -0.3103400041677401,
            -0.38944672083111465,
            19.0
        ],
        [
            -0.5610738377048543,
            2.343627074145597,
            -0.298698352180609,
            0.36283058476966806,
            -0.3103400041677401,
            -0.38944672083111465,
            16.0
        ],
        [
            -0.5610738377048543,
            2.343627074145597,
            -0.298698352180609,
            0.36283058476966806,
            -0.3103400041677401,
            -0.38944672083111465,
            2.0
        ],
        [
            2.753923954085216,
            -0.5967023705186999,
            -0.298698352180609,
            0.36283058476966806,
            -0.3103400041677401,
            -0.38944672083111465,
            18.0
        ],
        [
            2.753923954085216,
            -0.5967023705186999,
            -0.298698352180609,
            0.36283058476966806,
            -0.3103400041677401,
            -0.38944672083111465,
            12.0
        ],
        [
            2.753923954085216,
            -0.5967023705186999,
            -0.298698352180609,
            0.36283058476966806,
            -0.3103400041677401,
            -0.38944672083111465,
            22.0
        ],
        [
            2.753923954085216,
            -0.5967023705186999,
            -0.298698352180609,
            0.36283058476966806,
            -0.3103400041677401,
            -0.38944672083111465,
            4.0
        ],
        [
            2.753923954085216,
            -0.5967023705186999,
            -0.298698352180609,
            0.36283058476966806,
            -0.3103400041677401,
            -0.38944672083111465,
            26.0
        ],
        [
            2.753923954085216,
            -0.5967023705186999,
            -0.298698352180609,
            0.36283058476966806,
            -0.3103400041677401,
            -0.38944672083111465,
            27.0
        ],
        [
            2.753923954085216,
            -0.5967023705186999,
            -0.298698352180609,
            0.36283058476966806,
            -0.3103400041677401,
            -0.38944672083111465,
            23.0
        ],
        [
            2.753923954085216,
            -0.5967023705186999,
            -0.298698352180609,
            0.36283058476966806,
            -0.3103400041677401,
            -0.38944672083111465,
            7.0
        ],
        [
            2.753923954085216,
            -0.5967023705186999,
            -0.298698352180609,
            0.36283058476966806,
            -0.3103400041677401,
            -0.38944672083111465,
            12.0
        ],
        [
            2.753923954085216,
            -0.5967023705186999,
            -0.298698352180609,
            0.36283058476966806,
            -0.3103400041677401,
            -0.38944672083111465,
            1.0
        ],
        [
            2.753923954085216,
            -0.5967023705186999,
            -0.298698352180609,
            0.36283058476966806,
            -0.3103400041677401,
            -0.38944672083111465,
            8.0
        ],
        [
            2.753923954085216,
            -0.5967023705186999,
            -0.298698352180609,
            0.36283058476966806,
            -0.3103400041677401,
            -0.38944672083111465,
            17.0
        ],
        [
            -0.5610738377048543,
            -0.5967023705186999,
            -0.298698352180609,
            0.36283058476966806,
            -0.3103400041677401,
            -0.38944672083111465,
            8.0
        ],
        [
            -0.5610738377048543,
            -0.5967023705186999,
            -0.298698352180609,
            0.36283058476966806,
            -0.3103400041677401,
            -0.38944672083111465,
            4.0
        ],
        [
            -0.5610738377048543,
            -0.5967023705186999,
            -0.298698352180609,
            0.36283058476966806,
            -0.3103400041677401,
            -0.38944672083111465,
            5.0
        ],
        [
            -0.5610738377048543,
            -0.5967023705186999,
            -0.298698352180609,
            0.36283058476966806,
            -0.3103400041677401,
            -0.38944672083111465,
            18.0
        ],
        [
            -0.5610738377048543,
            -0.5967023705186999,
            -0.298698352180609,
            0.36283058476966806,
            -0.3103400041677401,
            -0.38944672083111465,
            20.0
        ],
        [
            -0.5610738377048543,
            -0.5967023705186999,
            -0.298698352180609,
            0.36283058476966806,
            -0.3103400041677401,
            -0.38944672083111465,
            14.0
        ],
        [
            -0.5610738377048543,
            -0.5967023705186999,
            -0.298698352180609,
            0.36283058476966806,
            -0.3103400041677401,
            -0.38944672083111465,
            27.0
        ],
        [
            -0.5610738377048543,
            -0.5967023705186999,
            -0.298698352180609,
            0.36283058476966806,
            -0.3103400041677401,
            -0.38944672083111465,
            10.0
        ],
        [
            -0.5610738377048543,
            -0.5967023705186999,
            -0.298698352180609,
            0.36283058476966806,
            -0.3103400041677401,
            -0.38944672083111465,
            2.0
        ],
        [
            -0.5610738377048543,
            -0.5967023705186999,
            -0.298698352180609,
            0.36283058476966806,
            -0.3103400041677401,
            -0.38944672083111465,
            25.0
        ],
        [
            -0.5610738377048543,
            -0.5967023705186999,
            -0.298698352180609,
            0.36283058476966806,
            -0.3103400041677401,
            -0.38944672083111465,
            16.0
        ],
        [
            -0.5610738377048543,
            -0.5967023705186999,
            -0.298698352180609,
            0.36283058476966806,
            -0.3103400041677401,
            -0.38944672083111465,
            22.0
        ],
        [
            0.6164053673026297,
            0.33856028245086706,
            0.4259835387193763,
            -3.1511364063756844,
            3.654231148099774,
            2.367484020419657,
            19.0
        ],
        [
            -0.02323091628275283,
            1.8131930382489534,
            2.4316958011602874,
            -3.131669872232762,
            1.4851829030122479,
            2.367484020419657,
            19.0
        ],
        [
            -0.07319246495209837,
            1.4322454798453284,
            2.3090063486944112,
            -2.0707728250288415,
            -0.008077035227676957,
            2.367484020419657,
            26.0
        ],
        [
            -0.2742563964450943,
            2.226824643527055,
            3.928050761050792,
            -3.151136406375779,
            -0.016562971821655677,
            2.367484020419657,
            26.0
        ],
        [
            1.8724972085964866,
            -0.596702370517372,
            -0.298698352180609,
            -2.3708534209003354,
            3.3939439494473795,
            2.367484020419657,
            26.0
        ],
        [
            0.04982482881979571,
            1.2910204223057895,
            0.5717945756545687,
            -1.0715912619939003,
            1.1401388748000902,
            2.367484020419657,
            25.0
        ],
        [
            -0.5186605590297608,
            1.9312959367433493,
            1.6023357644570473,
            -2.177955362430978,
            1.1033915589890457,
            2.367484020419657,
            22.0
        ],
        [
            2.7539239540852116,
            1.7882607045690018,
            1.7756149867674684,
            -2.905681679141031,
            1.3538428026605325,
            2.367484020419657,
            25.0
        ],
        [
            2.7539239540852116,
            2.343627074145597,
            3.6087520068593424,
            -3.1511364063757785,
            -0.3103400041677401,
            3.5490257666699883,
            14.0
        ],
        [
            -0.5610738377048543,
            -0.5967023705186999,
            -0.298698352180609,
            0.36283058476966806,
            -0.3103400041677401,
            -0.38944672083111465,
            13.0
        ],
        [
            -0.5610738377048543,
            -0.5967023705186999,
            -0.298698352180609,
            0.36283058476966806,
            -0.3103400041677401,
            -0.38944672083111465,
            8.0
        ],
        [
            -0.5610738377048543,
            -0.5967023705186999,
            -0.298698352180609,
            0.36283058476966806,
            -0.3103400041677401,
            -0.38944672083111465,
            17.0
        ],
        [
            -0.5610738377048543,
            -0.5967023705186999,
            -0.298698352180609,
            0.36283058476966806,
            -0.3103400041677401,
            -0.38944672083111465,
            27.0
        ],
        [
            -0.5610738377048543,
            -0.5967023705186999,
            -0.298698352180609,
            0.36283058476966806,
            -0.3103400041677401,
            -0.38944672083111465,
            24.0
        ],
        [
            -0.5610738377048543,
            -0.5967023705186999,
            -0.298698352180609,
            0.36283058476966806,
            -0.3103400041677401,
            -0.38944672083111465,
            21.0
        ],
        [
            -0.5610738377048543,
            -0.5967023705186999,
            -0.298698352180609,
            0.36283058476966806,
            -0.3103400041677401,
            -0.38944672083111465,
            18.0
        ],
        [
            -0.5610738377048543,
            -0.5967023705186999,
            -0.298698352180609,
            0.36283058476966806,
            -0.3103400041677401,
            -0.38944672083111465,
            3.0
        ],
        [
            -0.5610738377048543,
            -0.5967023705186999,
            -0.298698352180609,
            0.36283058476966806,
            -0.3103400041677401,
            -0.38944672083111465,
            29.0
        ],
        [
            -0.5610738377048543,
            -0.5967023705186999,
            -0.298698352180609,
            0.36283058476966806,
            -0.3103400041677401,
            -0.38944672083111465,
            5.0
        ],
        [
            -0.5610738377048543,
            -0.5967023705186999,
            -0.298698352180609,
            0.36283058476966806,
            -0.3103400041677401,
            -0.38944672083111465,
            1.0
        ],
        [
            -0.5610738377048543,
            -0.5967023705186999,
            -0.298698352180609,
            0.36283058476966806,
            -0.3103400041677401,
            -0.38944672083111465,
            10.0
        ],
        [
            -0.5610738377048543,
            -0.5967023705186999,
            -0.298698352180609,
            0.36283058476966806,
            -0.3103400041677401,
            -0.38944672083111465,
            23.0
        ],
        [
            -0.5610738377048543,
            -0.5967023705186999,
            -0.298698352180609,
            0.36283058476966806,
            -0.3103400041677401,
            -0.38944672083111465,
            0.0
        ],
        [
            -0.5610738377048543,
            -0.5967023705186999,
            -0.298698352180609,
            0.36283058476966806,
            -0.3103400041677401,
            -0.38944672083111465,
            27.0
        ],
        [
            -0.5610738377048543,
            -0.5967023705186999,
            -0.298698352180609,
            0.36283058476966806,
            -0.3103400041677401,
            -0.38944672083111465,
            5.0
        ],
        [
            -0.5610738377048543,
            -0.5967023705186999,
            -0.298698352180609,
            0.36283058476966806,
            -0.3103400041677401,
            -0.38944672083111465,
            20.0
        ],
        [
            -0.5610738377048543,
            -0.5967023705186999,
            -0.298698352180609,
            0.36283058476966806,
            -0.3103400041677401,
            -0.38944672083111465,
            11.0
        ],
        [
            -0.5610738377048543,
            -0.5967023705186999,
            -0.298698352180609,
            0.36283058476966806,
            -0.3103400041677401,
            -0.38944672083111465,
            16.0
        ],
        [
            -0.5610738377048543,
            -0.5967023705186999,
            -0.298698352180609,
            0.36283058476966806,
            -0.3103400041677401,
            -0.38944672083111465,
            2.0
        ],
        [
            -0.5610738377048543,
            -0.5967023705186999,
            -0.298698352180609,
            0.36283058476966806,
            -0.3103400041677401,
            -0.38944672083111465,
            8.0
        ],
        [
            -0.5610738377048543,
            -0.5967023705186999,
            -0.298698352180609,
            0.36283058476966806,
            -0.3103400041677401,
            -0.38944672083111465,
            13.0
        ],
        [
            -0.5610738377048543,
            -0.5967023705186999,
            -0.298698352180609,
            0.36283058476966806,
            -0.3103400041677401,
            -0.38944672083111465,
            28.0
        ],
        [
            -0.5610738377048543,
            -0.5967023705186999,
            -0.298698352180609,
            0.36283058476966806,
            -0.3103400041677401,
            -0.38944672083111465,
            19.0
        ],
        [
            -0.5610738377048543,
            -0.5967023705186999,
            -0.298698352180609,
            0.36283058476966806,
            -0.3103400041677401,
            -0.38944672083111465,
            24.0
        ],
        [
            -0.5610738377048543,
            -0.5967023705186999,
            -0.298698352180609,
            0.36283058476966806,
            -0.3103400041677401,
            -0.38944672083111465,
            6.0
        ],
        [
            -0.5610738377048543,
            -0.5967023705186999,
            -0.298698352180609,
            0.36283058476966806,
            -0.3103400041677401,
            -0.38944672083111465,
            12.0
        ],
        [
            -0.5610738377048543,
            -0.5967023705186999,
            -0.298698352180609,
            0.36283058476966806,
            -0.3103400041677401,
            -0.38944672083111465,
            13.0
        ],
        [
            -0.5610738377048543,
            -0.5967023705186999,
            -0.298698352180609,
            0.36283058476966806,
            -0.3103400041677401,
            -0.38944672083111465,
            4.0
        ],
        [
            -0.5610738377048543,
            -0.5967023705186999,
            -0.298698352180609,
            0.36283058476966806,
            -0.3103400041677401,
            -0.38944672083111465,
            1.0
        ],
        [
            -0.5610738377048543,
            -0.5967023705186999,
            -0.298698352180609,
            0.36283058476966806,
            -0.3103400041677401,
            -0.38944672083111465,
            16.0
        ],
        [
            -0.5610738377048543,
            -0.5967023705186999,
            -0.298698352180609,
            0.36283058476966806,
            -0.3103400041677401,
            -0.38944672083111465,
            25.0
        ],
        [
            -0.5610738377048543,
            -0.5967023705186999,
            -0.298698352180609,
            0.36283058476966806,
            -0.3103400041677401,
            -0.38944672083111465,
            21.0
        ],
        [
            -0.5610738377048543,
            -0.5967023705186999,
            -0.298698352180609,
            0.36283058476966806,
            -0.3103400041677401,
            -0.38944672083111465,
            18.0
        ],
        [
            -0.5610738377048543,
            -0.5967023705186999,
            -0.298698352180609,
            0.36283058476966806,
            -0.3103400041677401,
            -0.38944672083111465,
            28.0
        ],
        [
            -0.5610738377048543,
            -0.5967023705186999,
            -0.298698352180609,
            0.36283058476966806,
            -0.3103400041677401,
            -0.38944672083111465,
            8.0
        ],
        [
            -0.5610738377048543,
            -0.5967023705186999,
            -0.298698352180609,
            0.36283058476966806,
            -0.3103400041677401,
            -0.38944672083111465,
            6.0
        ],
        [
            -0.5610738377048543,
            -0.5967023705186999,
            -0.298698352180609,
            0.36283058476966806,
            -0.3103400041677401,
            -0.38944672083111465,
            1.0
        ],
        [
            -0.5610738377048543,
            -0.5967023705186999,
            -0.298698352180609,
            0.36283058476966806,
            -0.3103400041677401,
            -0.38944672083111465,
            21.0
        ],
        [
            -0.5610738377048543,
            -0.5967023705186999,
            -0.298698352180609,
            0.36283058476966806,
            -0.3103400041677401,
            -0.38944672083111465,
            27.0
        ],
        [
            -0.5610738377048543,
            -0.5967023705186999,
            -0.298698352180609,
            0.36283058476966806,
            -0.3103400041677401,
            -0.38944672083111465,
            28.0
        ],
        [
            -0.5610738377048543,
            -0.5967023705186999,
            -0.298698352180609,
            0.36283058476966806,
            -0.3103400041677401,
            -0.38944672083111465,
            13.0
        ],
        [
            -0.5610738377048543,
            -0.5967023705186999,
            -0.298698352180609,
            0.36283058476966806,
            -0.3103400041677401,
            -0.38944672083111465,
            4.0
        ],
        [
            -0.5610738377048543,
            -0.5967023705186999,
            -0.298698352180609,
            0.36283058476966806,
            -0.3103400041677401,
            -0.38944672083111465,
            18.0
        ],
        [
            -0.5610738377048543,
            -0.5967023705186999,
            -0.298698352180609,
            0.36283058476966806,
            -0.3103400041677401,
            -0.38944672083111465,
            22.0
        ],
        [
            -0.5610738377048543,
            -0.5967023705186999,
            -0.298698352180609,
            0.36283058476966806,
            -0.3103400041677401,
            -0.38944672083111465,
            8.0
        ],
        [
            -0.5610738377048543,
            -0.5967023705186999,
            -0.298698352180609,
            0.36283058476966806,
            -0.3103400041677401,
            -0.38944672083111465,
            16.0
        ],
        [
            -0.5610738377048543,
            -0.5967023705186999,
            -0.298698352180609,
            0.36283058476966806,
            -0.3103400041677401,
            -0.38944672083111465,
            11.0
        ],
        [
            -0.5610738377048543,
            -0.5967023705186999,
            -0.298698352180609,
            0.36283058476966806,
            -0.3103400041677401,
            -0.38944672083111465,
            21.0
        ],
        [
            -0.5610738377048543,
            -0.5967023705186999,
            -0.298698352180609,
            0.36283058476966806,
            -0.3103400041677401,
            -0.38944672083111465,
            8.0
        ],
        [
            -0.5610738377048543,
            -0.5967023705186999,
            -0.298698352180609,
            0.36283058476966806,
            -0.3103400041677401,
            -0.38944672083111465,
            14.0
        ],
        [
            -0.5610738377048543,
            -0.5967023705186999,
            -0.298698352180609,
            0.36283058476966806,
            -0.3103400041677401,
            -0.38944672083111465,
            4.0
        ],
        [
            -0.5610738377048543,
            -0.5967023705186999,
            -0.298698352180609,
            0.36283058476966806,
            -0.3103400041677401,
            -0.38944672083111465,
            1.0
        ],
        [
            -0.5610738377048543,
            -0.5967023705186999,
            -0.298698352180609,
            0.36283058476966806,
            -0.3103400041677401,
            -0.38944672083111465,
            15.0
        ],
        [
            -0.5610738377048543,
            -0.5967023705186999,
            -0.298698352180609,
            0.36283058476966806,
            -0.3103400041677401,
            -0.38944672083111465,
            22.0
        ],
        [
            -0.5610738377048543,
            -0.5967023705186999,
            -0.298698352180609,
            0.36283058476966806,
            -0.3103400041677401,
            -0.38944672083111465,
            7.0
        ],
        [
            -0.5610738377048543,
            -0.5967023705186999,
            -0.298698352180609,
            0.36283058476966806,
            -0.3103400041677401,
            -0.38944672083111465,
            26.0
        ],
        [
            -0.5610738377048543,
            -0.5967023705186999,
            -0.298698352180609,
            0.36283058476966806,
            -0.3103400041677401,
            -0.38944672083111465,
            29.0
        ],
        [
            -0.5610738377048543,
            -0.5967023705186999,
            -0.298698352180609,
            0.36283058476966806,
            -0.3103400041677401,
            -0.38944672083111465,
            10.0
        ],
        [
            -0.5610738377048543,
            -0.5967023705186999,
            -0.298698352180609,
            0.36283058476966806,
            -0.3103400041677401,
            -0.38944672083111465,
            17.0
        ],
        [
            -0.5610738377048543,
            -0.5967023705186999,
            -0.298698352180609,
            0.36283058476966806,
            -0.3103400041677401,
            -0.38944672083111465,
            16.0
        ],
        [
            -0.5610738377048543,
            -0.5967023705186999,
            -0.298698352180609,
            0.36283058476966806,
            -0.3103400041677401,
            -0.38944672083111465,
            23.0
        ],
        [
            -0.5610738377048543,
            -0.5967023705186999,
            -0.298698352180609,
            0.36283058476966806,
            -0.3103400041677401,
            -0.38944672083111465,
            25.0
        ],
        [
            -0.5610738377048543,
            -0.5967023705186999,
            -0.298698352180609,
            0.36283058476966806,
            -0.3103400041677401,
            -0.38944672083111465,
            13.0
        ],
        [
            -0.5610738377048543,
            -0.5967023705186999,
            -0.298698352180609,
            0.36283058476966806,
            -0.3103400041677401,
            -0.38944672083111465,
            2.0
        ],
        [
            -0.5610738377048543,
            -0.5967023705186999,
            -0.298698352180609,
            0.36283058476966806,
            -0.3103400041677401,
            -0.38944672083111465,
            7.0
        ],
        [
            -0.5610738377048543,
            -0.5967023705186999,
            -0.298698352180609,
            0.36283058476966806,
            -0.3103400041677401,
            -0.38944672083111465,
            5.0
        ],
        [
            -0.5610738377048543,
            -0.5967023705186999,
            -0.298698352180609,
            0.36283058476966806,
            -0.3103400041677401,
            -0.38944672083111465,
            10.0
        ],
        [
            -0.5610738377048543,
            -0.5967023705186999,
            -0.298698352180609,
            0.36283058476966806,
            -0.3103400041677401,
            -0.38944672083111465,
            22.0
        ],
        [
            -0.5610738377048543,
            -0.5967023705186999,
            -0.298698352180609,
            0.36283058476966806,
            -0.3103400041677401,
            -0.38944672083111465,
            1.0
        ],
        [
            -0.5610738377048543,
            -0.5967023705186999,
            -0.298698352180609,
            0.36283058476966806,
            -0.3103400041677401,
            -0.38944672083111465,
            29.0
        ],
        [
            -0.5610738377048543,
            -0.5967023705186999,
            -0.298698352180609,
            0.36283058476966806,
            -0.3103400041677401,
            -0.38944672083111465,
            19.0
        ],
        [
            -0.5610738377048543,
            -0.5967023705186999,
            -0.29869835218060903,
            0.36283058476966806,
            -0.31034000416774016,
            -0.38944672083111465,
            11.0
        ],
        [
            -0.5610738377048543,
            -0.5967023705186999,
            -0.29869835218060903,
            0.36283058476966806,
            -0.31034000416774016,
            -0.38944672083111465,
            0.0
        ],
        [
            -0.5610738377048543,
            -0.5967023705186999,
            -0.29869835218060903,
            0.36283058476966806,
            -0.31034000416774016,
            -0.38944672083111465,
            22.0
        ],
        [
            -0.5610738377048543,
            -0.5967023705186999,
            -0.29869835218060903,
            0.36283058476966806,
            -0.31034000416774016,
            -0.38944672083111465,
            27.0
        ],
        [
            -0.5610738377048543,
            -0.5967023705186999,
            -0.29869835218060903,
            0.36283058476966806,
            -0.31034000416774016,
            -0.38944672083111465,
            3.0
        ],
        [
            -0.5610738377048543,
            -0.5967023705186999,
            -0.29869835218060903,
            0.36283058476966806,
            -0.31034000416774016,
            -0.38944672083111465,
            12.0
        ],
        [
            -0.5610738377048543,
            -0.5967023705186999,
            -0.29869835218060903,
            0.36283058476966806,
            -0.31034000416774016,
            -0.38944672083111465,
            21.0
        ],
        [
            -0.5610738377048543,
            -0.5967023705186999,
            -0.29869835218060903,
            0.36283058476966806,
            -0.31034000416774016,
            -0.38944672083111465,
            16.0
        ],
        [
            -0.5610738377048543,
            -0.5967023705186999,
            -0.29869835218060903,
            0.36283058476966806,
            -0.31034000416774016,
            -0.38944672083111465,
            7.0
        ],
        [
            -0.5610738377048543,
            -0.5967023705186999,
            -0.29869835218060903,
            0.36283058476966806,
            -0.31034000416774016,
            -0.38944672083111465,
            28.0
        ],
        [
            -0.5610738377048543,
            -0.5967023705186999,
            -0.29869835218060903,
            0.36283058476966806,
            -0.31034000416774016,
            -0.38944672083111465,
            8.0
        ],
        [
            -0.5610738377048543,
            -0.5967023705186999,
            -0.29869835218060903,
            0.36283058476966806,
            -0.31034000416774016,
            -0.38944672083111465,
            19.0
        ],
        [
            -0.5610738377048543,
            -0.5967023705186999,
            -0.21569714424505226,
            0.36283058476966806,
            -0.3103400041677401,
            3.5490257666699883,
            25.0
        ]
    ],
    "ytrain": [
        [
            -1.4136474679798077
        ],
        [
            1.119249394520549
        ],
        [
            -1.042349324596078
        ],
        [
            -0.49203030194373065
        ],
        [
            1.351334069353878
        ],
        [
            1.2444677822762558
        ],
        [
            0.03989229156637537
        ],
        [
            -0.3704295151615151
        ],
        [
            -1.0994465280990913
        ],
        [
            -0.6496047141713293
        ],
        [
            -1.070377791803723
        ],
        [
            -0.6276675385148623
        ],
        [
            3.0371639535546255
        ],
        [
            0.879800926706926
        ],
        [
            0.8798028815281013
        ],
        [
            1.1000656650115754
        ],
        [
            0.8797384226815447
        ],
        [
            -0.6624913263432918
        ],
        [
            -0.4279205892686514
        ],
        [
            -0.08256182298010153
        ],
        [
            -1.251245128400297
        ],
        [
            -1.0869538953959095
        ],
        [
            0.7548679293449935
        ],
        [
            0.7400752524390383
        ],
        [
            -0.2707600058773776
        ],
        [
            -0.6318443635316661
        ],
        [
            0.498846782144754
        ],
        [
            0.30639049493610915
        ],
        [
            0.6795107118948913
        ],
        [
            0.6518097653397653
        ],
        [
            -0.7360092280509819
        ],
        [
            -0.18851487283337032
        ],
        [
            -0.21249774213083306
        ],
        [
            -0.1010250122734729
        ],
        [
            -0.08534773431740593
        ],
        [
            -0.3314709442227774
        ],
        [
            1.0824996396666473
        ],
        [
            2.3882782812809293
        ],
        [
            -0.7025633747147294
        ],
        [
            -1.2930192780892382
        ],
        [
            1.162974292661404
        ],
        [
            -0.006560280864508124
        ],
        [
            1.1692737440195653
        ],
        [
            0.8089906721344067
        ],
        [
            1.4538304213322
        ],
        [
            0.3775127980683055
        ],
        [
            -0.8646467539673097
        ],
        [
            -0.21697858332440198
        ],
        [
            0.6314325488963177
        ],
        [
            -1.336752923806265
        ],
        [
            1.2807968923909538
        ],
        [
            -0.5546767720539963
        ],
        [
            1.2522842909832337
        ],
        [
            0.972992597991032
        ],
        [
            0.23561966327429423
        ],
        [
            -1.1396841148597525
        ],
        [
            1.3760730438019928
        ],
        [
            -0.9269007752849912
        ],
        [
            -0.40354051112431993
        ],
        [
            -1.0979848395801588
        ],
        [
            -1.0842192734655407
        ],
        [
            -0.7437600251562999
        ],
        [
            -1.1677473932727567
        ],
        [
            -0.9533451987748901
        ],
        [
            0.7200295660129673
        ],
        [
            -0.32783510162507606
        ],
        [
            0.5060598583322448
        ],
        [
            -0.7179255163987293
        ],
        [
            0.2684867092765284
        ],
        [
            -1.0605120065565294
        ],
        [
            0.23479785203483836
        ],
        [
            -1.3756774097975197
        ],
        [
            0.4920103643975986
        ],
        [
            -1.400428764453512
        ],
        [
            1.699627435103014
        ],
        [
            0.6699505509492368
        ],
        [
            -0.6254887063097772
        ],
        [
            -0.785594667649151
        ],
        [
            0.7942190202614083
        ],
        [
            1.12309531573051
        ],
        [
            -1.021457163799224
        ],
        [
            -1.127767833203791
        ],
        [
            2.236020971830438
        ],
        [
            -1.1718901877621042
        ],
        [
            -1.0921885987637825
        ],
        [
            -0.4734820442878026
        ],
        [
            -0.4737180502293423
        ],
        [
            -0.3532271018252646
        ],
        [
            -0.4163118707304134
        ],
        [
            -0.4192155413948824
        ],
        [
            1.0821244513701542
        ],
        [
            -0.961973676634261
        ],
        [
            1.081534106155861
        ],
        [
            0.7303923702505042
        ],
        [
            0.19407302142222987
        ],
        [
            -1.385334051873337
        ],
        [
            -0.4600092713463812
        ],
        [
            1.1937538920546906
        ],
        [
            -0.5104795268824995
        ],
        [
            0.06625990588994925
        ],
        [
            -0.7941595886564229
        ],
        [
            1.6360520747694962
        ],
        [
            0.34245724744290335
        ],
        [
            0.8441559102003547
        ],
        [
            0.5323826176559738
        ],
        [
            -1.0658281704990136
        ],
        [
            -0.5391110333051682
        ],
        [
            0.025560289629348892
        ],
        [
            1.3332806074090287
        ],
        [
            0.2084376222986828
        ],
        [
            -0.9079596280788563
        ],
        [
            -1.3041361461767207
        ],
        [
            -1.1496894657328818
        ],
        [
            -1.00881978271769
        ],
        [
            -1.353059312287674
        ],
        [
            0.4866810437003181
        ],
        [
            0.11795928444177994
        ],
        [
            -0.3828067155952842
        ],
        [
            -0.8014833648441719
        ],
        [
            1.8191702684697937
        ],
        [
            -1.1332430659085106
        ],
        [
            0.76475319500204
        ],
        [
            1.7204192331344876
        ],
        [
            1.2134507059794097
        ],
        [
            -1.0995499326523224
        ],
        [
            1.6689604685972679
        ],
        [
            -0.16047773883207642
        ],
        [
            -0.8193188527434424
        ],
        [
            -0.21338373258015578
        ],
        [
            -1.3667874502165271
        ],
        [
            0.7264884864985816
        ],
        [
            1.594434860628466
        ],
        [
            -0.3919085933920529
        ],
        [
            0.7663907571507821
        ],
        [
            0.45702641056813154
        ],
        [
            0.2346903936606072
        ],
        [
            1.9267457181727923
        ],
        [
            -0.647324077978794
        ],
        [
            -0.971873812919059
        ],
        [
            -1.4062626158243523
        ],
        [
            -1.2166522089765284
        ],
        [
            -1.319507636121625
        ],
        [
            -0.634829535905332
        ],
        [
            -1.3575560011972998
        ],
        [
            0.5031850803818896
        ],
        [
            1.9875173988730055
        ],
        [
            0.830433298356036
        ],
        [
            0.24569655023529768
        ],
        [
            -0.9917503899743912
        ],
        [
            0.3962057208837844
        ],
        [
            -0.189910948391104
        ],
        [
            1.7792285473863048
        ],
        [
            -1.0689099660927892
        ],
        [
            0.2170386225902302
        ],
        [
            -1.1069341302262354
        ],
        [
            -0.5822934585444705
        ],
        [
            1.7871692295706236
        ],
        [
            0.45885126359768547
        ],
        [
            -1.0961578276231656
        ],
        [
            0.45505234048310433
        ],
        [
            1.1206248795483271
        ],
        [
            -1.082983921516093
        ],
        [
            -0.8043782616955549
        ],
        [
            1.1321480027046014
        ],
        [
            0.7165006236859572
        ],
        [
            -0.17299974250248823
        ],
        [
            -1.2718719176939566
        ],
        [
            0.2659792512183373
        ],
        [
            -0.9666069643818865
        ],
        [
            0.8793339427770429
        ],
        [
            2.0574624440122826
        ],
        [
            -1.0429317236296394
        ],
        [
            -0.07465719831100512
        ],
        [
            -1.0857209559380763
        ],
        [
            0.6843454415545669
        ],
        [
            -0.0022575018017638253
        ],
        [
            -1.395812555410853
        ],
        [
            -0.48541953835189794
        ],
        [
            1.5701380688439857
        ]
    ],
    "X_mean": [
        31.692531557922635,
        6.4058744992684495,
        0.0035853867248082606,
        44.83730800995094,
        1.594688551414214,
        0.9888268156424581
    ],
    "X_std": [
        3.01659326131861,
        0.6801958888073999,
        0.012003369615646036,
        14.228932749223553,
        5.138520751428095,
        2.5390554413507758
    ],
    "y_mean": 4.734215119690117,
    "y_std": 3.020146621517895,
    "error": null
}