{
    "clone distribution": "alpha",
    "mbr_level": 7.0,
    "n_iterations": {
        "0": 12,
        "7.0": 4,
        "10": 1
    },
    "iterations": 20,
    "best_values": [
        1.9094255286049158,
        9.08308956814224,
        9.774310477531838,
        24.716218868987472,
        24.716218868987472,
        24.716218868987472,
        24.716218868987472,
        24.716218868987472,
        24.716218868987472,
        24.716218868987472,
        24.716218868987472,
        24.716218868987472,
        24.716218868987472,
        24.716218868987472,
        24.716218868987472,
        24.716218868987472,
        24.716218868987472,
        24.716218868987472,
        24.716218868987472,
        24.716218868987472,
        24.716218868987472
    ],
    "batches": [
        [
            [
                35.11820989214304,
                7.900889444147131,
                0.0,
                50.0,
                0.0,
                0.0,
                5.0
            ],
            [
                35.118123965188495,
                7.900837898504442,
                0.0,
                50.0,
                0.0,
                0.0,
                13.0
            ],
            [
                35.11815471551118,
                7.900908933954366,
                0.0,
                50.0,
                0.0,
                0.0,
                25.0
            ],
            [
                35.11817404652712,
                7.900870406955432,
                0.0,
                50.0,
                0.0,
                0.0,
                10.0
            ],
            [
                35.11818264866931,
                7.900922382716304,
                0.0,
                50.0,
                0.0,
                0.0,
                15.0
            ],
            [
                35.118162851598505,
                7.900835379693985,
                0.0,
                50.0,
                0.0,
                0.0,
                20.0
            ],
            [
                35.11812797339334,
                7.900911620986699,
                0.0,
                50.0,
                0.0,
                0.0,
                0.0
            ],
            [
                35.118195508596095,
                7.900854054951662,
                0.0,
                50.0,
                0.0,
                0.0,
                22.0
            ],
            [
                35.118144278149515,
                7.900855354752587,
                0.0,
                50.0,
                0.0,
                0.0,
                28.0
            ],
            [
                35.11813542365353,
                7.9008982687372376,
                0.0,
                50.0,
                0.0,
                0.0,
                17.0
            ],
            [
                35.118203211850144,
                7.900875275085771,
                0.0,
                50.0,
                0.0,
                0.0,
                4.0
            ],
            [
                35.1181686705507,
                7.90086733381148,
                19.693404016125186,
                20.207182026991834,
                10.099413956882987,
                7.0,
                23.0
            ]
        ],
        [
            [
                38.63830403524618,
                6.1893284666997905,
                19.854752188024037,
                0.9623936132979836,
                6.437324170259037,
                7.0,
                25.0
            ],
            [
                30.280264845611015,
                7.175320242722065,
                5.278529006887355,
                29.487894686110423,
                5.084754727466501,
                7.0,
                5.0
            ],
            [
                39.02161362978721,
                6.289831126051753,
                3.4452253905526313,
                28.628962119378677,
                5.778505086917677,
                7.0,
                6.0
            ],
            [
                39.90530821686298,
                6.076707883394107,
                3.989083126087834,
                39.250384281324166,
                1.584670572786752,
                7.0,
                10.0
            ]
        ],
        [
            [
                30.0,
                6.0,
                0.0,
                50.0,
                0.0,
                0.0,
                12.0
            ],
            [
                30.0,
                6.0,
                0.0,
                50.0,
                0.0,
                0.0,
                23.0
            ],
            [
                30.0,
                6.0,
                0.0,
                50.0,
                0.0,
                0.0,
                25.0
            ],
            [
                30.0,
                6.0,
                0.0,
                50.0,
                0.0,
                0.0,
                0.0
            ],
            [
                30.0,
                6.0,
                0.0,
                50.0,
                0.0,
                0.0,
                18.0
            ],
            [
                30.0,
                6.0,
                0.0,
                50.0,
                0.0,
                0.0,
                9.0
            ],
            [
                30.0,
                6.0,
                0.0,
                50.0,
                0.0,
                0.0,
                29.0
            ],
            [
                30.0,
                6.0,
                0.0,
                50.0,
                0.0,
                0.0,
                20.0
            ],
            [
                30.0,
                6.0,
                0.0,
                50.0,
                0.0,
                0.0,
                14.0
            ],
            [
                30.0,
                6.0,
                0.0,
                50.0,
                0.0,
                0.0,
                5.0
            ],
            [
                30.0,
                6.0,
                0.0,
                50.0,
                0.0,
                0.0,
                3.0
            ],
            [
                30.0,
                6.0,
                0.0,
                50.0,
                0.0,
                0.0,
                16.0
            ]
        ],
        [
            [
                30.0,
                6.0,
                0.2732709507990472,
                50.0,
                0.1342933066700639,
                7.0,
                4.0
            ],
            [
                39.719842023297666,
                6.000000000000074,
                2.511324481702104e-13,
                50.0,
                0.2672440215826559,
                7.0,
                26.0
            ],
            [
                30.0,
                8.0,
                -2.220446049250313e-16,
                23.189185589373793,
                7.127082702594327,
                7.0,
                26.0
            ],
            [
                30.0,
                7.9999999999972,
                25.065766618092365,
                1.9895196601282805e-13,
                6.461498003318411e-14,
                7.0,
                7.0
            ]
        ],
        [
            [
                30.0,
                6.0,
                0.3382225811001729,
                50.0,
                0.23792086265629864,
                10.0,
                5.0
            ]
        ],
        [
            [
                30.0,
                6.0,
                0.37524656127108225,
                50.0,
                0.20373920332227613,
                10.0,
                4.0
            ]
        ],
        [
            [
                40.0,
                8.0,
                26.006732909580194,
                0.0,
                4.440892098500626e-16,
                10.0,
                5.0
            ]
        ],
        [
            [
                30.0,
                6.180058466748682,
                4.0826523532263295,
                43.65315453651485,
                0.0,
                10.0,
                7.0
            ]
        ],
        [
            [
                37.73621845738685,
                7.6228654863134855,
                26.06035416000552,
                0.0,
                0.5598412129092523,
                10.0,
                7.0
            ]
        ],
        [
            [
                38.18337317473045,
                6.040844981158523,
                28.883629200707034,
                0.0,
                0.0,
                10.0,
                7.0
            ]
        ],
        [
            [
                39.99999999999996,
                8.0,
                30.360296210529395,
                0.0,
                0.0,
                10.0,
                4.0
            ]
        ],
        [
            [
                38.24189742711993,
                6.004169144188371,
                30.7089655909876,
                5.820481874252437e-10,
                0.07093194817173831,
                10.0,
                6.0
            ]
        ],
        [
            [
                30.000000000000043,
                6.0,
                0.0,
                50.0,
                0.3917602748039901,
                10.0,
                4.0
            ]
        ],
        [
            [
                30.000377238183813,
                6.099962326785656,
                26.874830503436478,
                1.4181449784276055,
                0.2329547270915331,
                10.0,
                4.0
            ]
        ],
        [
            [
                35.579579983655506,
                6.93351166974055,
                11.732840305153069,
                29.201395864153262,
                1.154927492906087,
                10.0,
                23.0
            ]
        ],
        [
            [
                30.000000000007663,
                6.000000000001815,
                33.35635156838181,
                0.0,
                1.4002254911105183e-10,
                10.0,
                25.0
            ]
        ],
        [
            [
                30.0,
                6.0,
                34.49468620064343,
                0.0,
                1.1246559239452836e-13,
                10.0,
                11.0
            ]
        ],
        [
            [
                30.0,
                6.0,
                35.572243932118866,
                7.105427357601002e-15,
                0.0,
                7.0,
                1.0
            ],
            [
                34.96433633468104,
                8.0,
                35.572245394459316,
                0.0,
                0.0,
                7.0,
                21.0
            ],
            [
                30.0,
                6.0,
                0.0,
                0.0,
                6.719147274348302,
                7.0,
                5.0
            ],
            [
                30.0,
                6.0,
                35.572243941742514,
                0.0,
                0.0,
                7.0,
                9.0
            ]
        ],
        [
            [
                30.0,
                6.0,
                36.86241896078677,
                0.0,
                0.0,
                10.0,
                10.0
            ]
        ],
        [
            [
                30.0,
                8.0,
                0.0,
                50.0,
                0.4100293811742872,
                10.0,
                26.0
            ]
        ],
        [
            [
                30.0,
                6.0,
                36.808640599093906,
                0.8198109337298867,
                0.0,
                10.0,
                10.0
            ]
        ]
    ],
    "best_points": [
        [
            35.11815471551118,
            7.900908933954366,
            0.0,
            50.0,
            0.0,
            0.0,
            25.0
        ],
        [
            39.02161362978721,
            6.289831126051753,
            3.4452253905526313,
            28.628962119378677,
            5.778505086917677,
            7.0,
            6.0
        ],
        [
            30.0,
            6.0,
            0.0,
            50.0,
            0.0,
            0.0,
            3.0
        ],
        [
            30.0,
            6.0,
            0.2732709507990472,
            50.0,
            0.1342933066700639,
            7.0,
            4.0
        ],
        [
            30.0,
            6.0,
            0.3382225811001729,
            50.0,
            0.23792086265629864,
            10.0,
            5.0
        ],
        [
            30.0,
            6.0,
            0.37524656127108225,
            50.0,
            0.20373920332227613,
            10.0,
            4.0
        ],
        [
            40.0,
            8.0,
            26.006732909580194,
            0.0,
            4.440892098500626e-16,
            10.0,
            5.0
        ],
        [
            30.0,
            6.180058466748682,
            4.0826523532263295,
            43.65315453651485,
            0.0,
            10.0,
            7.0
        ],
        [
            37.73621845738685,
            7.6228654863134855,
            26.06035416000552,
            0.0,
            0.5598412129092523,
            10.0,
            7.0
        ],
        [
            38.18337317473045,
            6.040844981158523,
            28.883629200707034,
            0.0,
            0.0,
            10.0,
            7.0
        ],
        [
            39.99999999999996,
            8.0,
            30.360296210529395,
            0.0,
            0.0,
            10.0,
            4.0
        ],
        [
            38.24189742711993,
            6.004169144188371,
            30.7089655909876,
            5.820481874252437e-10,
            0.07093194817173831,
            10.0,
            6.0
        ],
        [
            30.000000000000043,
            6.0,
            0.0,
            50.0,
            0.3917602748039901,
            10.0,
            4.0
        ],
        [
            30.000377238183813,
            6.099962326785656,
            26.874830503436478,
            1.4181449784276055,
            0.2329547270915331,
            10.0,
            4.0
        ],
        [
            35.579579983655506,
            6.93351166974055,
            11.732840305153069,
            29.201395864153262,
            1.154927492906087,
            10.0,
            23.0
        ],
        [
            30.000000000007663,
            6.000000000001815,
            33.35635156838181,
            0.0,
            1.4002254911105183e-10,
            10.0,
            25.0
        ],
        [
            30.0,
            6.0,
            34.49468620064343,
            0.0,
            1.1246559239452836e-13,
            10.0,
            11.0
        ],
        [
            30.0,
            6.0,
            35.572243941742514,
            0.0,
            0.0,
            7.0,
            9.0
        ],
        [
            30.0,
            6.0,
            36.86241896078677,
            0.0,
            0.0,
            10.0,
            10.0
        ],
        [
            30.0,
            8.0,
            0.0,
            50.0,
            0.4100293811742872,
            10.0,
            26.0
        ],
        [
            30.0,
            6.0,
            36.808640599093906,
            0.8198109337298867,
            0.0,
            10.0,
            10.0
        ]
    ],
    "cumulative_cost_list": [
        0,
        120,
        2420,
        2540,
        4840,
        6940,
        9040,
        11140,
        13240,
        15340,
        17440,
        19540,
        21640,
        23740,
        25840,
        27940,
        30040,
        32140,
        34440,
        36540,
        38640,
        40740
    ],
    "fidelities": [
        0,
        7.0,
        0,
        7.0,
        10,
        10,
        10,
        10,
        10,
        10,
        10,
        10,
        10,
        10,
        10,
        10,
        10,
        7.0,
        10,
        10,
        10
    ],
    "Xtrain": [
        [
            0.6073553677370915,
            1.2636162496952315,
            -0.7025901786533773,
            0.802418432403741,
            -0.3985031480144986,
            -1.0869671867966517,
            5.0
        ],
        [
            0.6073312361440335,
            1.2635592522988213,
            -0.7025901786533773,
            0.802418432403741,
            -0.3985031480144986,
            -1.0869671867966517,
            13.0
        ],
        [
            0.6073398720171117,
            1.2636378008528262,
            -0.7025901786533773,
            0.802418432403741,
            -0.3985031480144986,
            -1.0869671867966517,
            25.0
        ],
        [
            0.6073453009097399,
            1.2635951990243082,
            -0.7025901786533773,
            0.802418432403741,
            -0.3985031480144986,
            -1.0869671867966517,
            10.0
        ],
        [
            0.6073477167220517,
            1.2636526720305912,
            -0.7025901786533773,
            0.802418432403741,
            -0.3985031480144986,
            -1.0869671867966517,
            15.0
        ],
        [
            0.6073421569432961,
            1.2635564670849688,
            -0.7025901786533773,
            0.802418432403741,
            -0.3985031480144986,
            -1.0869671867966517,
            20.0
        ],
        [
            0.6073323618020854,
            1.2636407720806369,
            -0.7025901786533773,
            0.802418432403741,
            -0.3985031480144986,
            -1.0869671867966517,
            0.0
        ],
        [
            0.6073513282840062,
            1.2635771175417154,
            -0.7025901786533773,
            0.802418432403741,
            -0.3985031480144986,
            -1.0869671867966517,
            22.0
        ],
        [
            0.6073369408045992,
            1.2635785548168128,
            -0.7025901786533773,
            0.802418432403741,
            -0.3985031480144986,
            -1.0869671867966517,
            28.0
        ],
        [
            0.6073344541216363,
            1.263626007623045,
            -0.7025901786533773,
            0.802418432403741,
            -0.3985031480144986,
            -1.0869671867966517,
            17.0
        ],
        [
            0.6073534916539628,
            1.2636005820351743,
            -0.7025901786533773,
            0.802418432403741,
            -0.3985031480144986,
            -1.0869671867966517,
            4.0
        ],
        [
            0.607343791128834,
            1.263591800847567,
            0.7046951408248846,
            -0.5297210697460057,
            4.102707211365677,
            0.4893517613865405,
            23.0
        ],
        [
            1.5959331642533545,
            -0.6289689315535181,
            0.7162250375076514,
            -1.3902218414293637,
            2.4705494886596044,
            0.4893517613865405,
            25.0
        ],
        [
            -0.7513256388882676,
            0.46130681597841927,
            -0.3253879248555936,
            -0.1147484427016637,
            1.8677224717979393,
            0.4893517613865405,
            5.0
        ],
        [
            1.703581238125853,
            -0.5178365522389936,
            -0.4563953049561464,
            -0.15315427604253382,
            2.1769202448684397,
            0.4893517613865405,
            6.0
        ],
        [
            1.9517566596259688,
            -0.7535008938244824,
            -0.41753137841116233,
            0.3217660904617466,
            0.3077690801449761,
            0.4893517613865405,
            10.0
        ],
        [
            -0.830034784795048,
            -0.8383218293970863,
            -0.7025901786533773,
            0.802418432403741,
            -0.3985031480144986,
            -1.0869671867966517,
            12.0
        ],
        [
            -0.830034784795048,
            -0.8383218293970863,
            -0.7025901786533773,
            0.802418432403741,
            -0.3985031480144986,
            -1.0869671867966517,
            23.0
        ],
        [
            -0.830034784795048,
            -0.8383218293970863,
            -0.7025901786533773,
            0.802418432403741,
            -0.3985031480144986,
            -1.0869671867966517,
            25.0
        ],
        [
            -0.830034784795048,
            -0.8383218293970863,
            -0.7025901786533773,
            0.802418432403741,
            -0.3985031480144986,
            -1.0869671867966517,
            0.0
        ],
        [
            -0.830034784795048,
            -0.8383218293970863,
            -0.7025901786533773,
            0.802418432403741,
            -0.3985031480144986,
            -1.0869671867966517,
            18.0
        ],
        [
            -0.830034784795048,
            -0.8383218293970863,
            -0.7025901786533773,
            0.802418432403741,
            -0.3985031480144986,
            -1.0869671867966517,
            9.0
        ],
        [
            -0.830034784795048,
            -0.8383218293970863,
            -0.7025901786533773,
            0.802418432403741,
            -0.3985031480144986,
            -1.0869671867966517,
            29.0
        ],
        [
            -0.830034784795048,
            -0.8383218293970863,
            -0.7025901786533773,
            0.802418432403741,
            -0.3985031480144986,
            -1.0869671867966517,
            20.0
        ],
        [
            -0.830034784795048,
            -0.8383218293970863,
            -0.7025901786533773,
            0.802418432403741,
            -0.3985031480144986,
            -1.0869671867966517,
            14.0
        ],
        [
            -0.830034784795048,
            -0.8383218293970863,
            -0.7025901786533773,
            0.802418432403741,
            -0.3985031480144986,
            -1.0869671867966517,
            5.0
        ],
        [
            -0.830034784795048,
            -0.8383218293970863,
            -0.7025901786533773,
            0.802418432403741,
            -0.3985031480144986,
            -1.0869671867966517,
            3.0
        ],
        [
            -0.830034784795048,
            -0.8383218293970863,
            -0.7025901786533773,
            0.802418432403741,
            -0.3985031480144986,
            -1.0869671867966517,
            16.0
        ],
        [
            -0.830034784795048,
            -0.8383218293970863,
            -0.6830623104907948,
            0.802418432403741,
            -0.33864993021796086,
            0.4893517613865405,
            4.0
        ],
        [
            1.8996706205857106,
            -0.8383218293970048,
            -0.7025901786533594,
            0.802418432403741,
            -0.27939509248119204,
            0.4893517613865405,
            26.0
        ],
        [
            -0.830034784795048,
            1.3732092889056837,
            -0.7025901786533773,
            -0.3963854200401187,
            2.777968143293769,
            0.4893517613865405,
            26.0
        ],
        [
            -0.830034784795048,
            1.3732092889025873,
            1.0886027179238902,
            -1.4332537744963236,
            -0.3985031480144698,
            0.4893517613865405,
            7.0
        ],
        [
            -0.830034784795048,
            -0.8383218293970863,
            -0.6784208845735633,
            0.802418432403741,
            -0.29246413859540904,
            1.164917024893623,
            5.0
        ],
        [
            -0.830034784795048,
            -0.8383218293970863,
            -0.6757751609738996,
            0.802418432403741,
            -0.3076985709844536,
            1.164917024893623,
            4.0
        ],
        [
            1.9783497535934136,
            1.3732092889056837,
            1.1558439143696875,
            -1.4332537744963325,
            -0.3985031480144984,
            1.164917024893623,
            5.0
        ],
        [
            -0.830034784795048,
            -0.6392193782327887,
            -0.41084494677145644,
            0.5186291123196696,
            -0.3985031480144986,
            1.164917024893623,
            7.0
        ],
        [
            1.3425928453370177,
            0.9561869325038294,
            1.1596756744084213,
            -1.4332537744963325,
            -0.14898737631591655,
            1.164917024893623,
            7.0
        ],
        [
            1.4681710847825409,
            -0.7931568559678042,
            1.3614261444833442,
            -1.4332537744963325,
            -0.3985031480144986,
            1.164917024893623,
            7.0
        ],
        [
            1.9783497535934016,
            1.3732092889056837,
            1.4669483692332812,
            -1.4332537744963325,
            -0.3985031480144986,
            1.164917024893623,
            4.0
        ],
        [
            1.4846069453356774,
            -0.83371173334245,
            1.4918641887670012,
            -1.433253774470307,
            -0.36688947010360856,
            1.164917024893623,
            6.0
        ],
        [
            -0.830034784795036,
            -0.8383218293970863,
            -0.7025901786533773,
            0.802418432403741,
            -0.22389941210766914,
            1.164917024893623,
            4.0
        ],
        [
            -0.8299288418067771,
            -0.727786931224872,
            1.2178779334101764,
            -1.3698436282238224,
            -0.29467749681061267,
            1.164917024893623,
            4.0
        ],
        [
            0.7369258308849389,
            0.1939232240679164,
            0.1358354131693973,
            -0.12755879177284843,
            0.11623677824220313,
            1.164917024893623,
            23.0
        ],
        [
            -0.8300347847928958,
            -0.8383218293950789,
            1.681045673995705,
            -1.4332537744963325,
            -0.3985031479520919,
            1.164917024893623,
            25.0
        ],
        [
            -0.830034784795048,
            -0.8383218293970863,
            1.7623907586404803,
            -1.4332537744963325,
            -0.39850314801444847,
            1.164917024893623,
            11.0
        ],
        [
            -0.830034784795048,
            -0.8383218293970863,
            1.8393927424089547,
            -1.433253774496332,
            -0.3985031480144986,
            0.4893517613865405,
            1.0
        ],
        [
            0.5641417557727809,
            1.3732092889056837,
            1.8393928469074075,
            -1.4332537744963325,
            -0.3985031480144986,
            0.4893517613865405,
            21.0
        ],
        [
            -0.830034784795048,
            -0.8383218293970863,
            -0.7025901786533773,
            -1.4332537744963325,
            2.5961552991605923,
            0.4893517613865405,
            5.0
        ],
        [
            -0.830034784795048,
            -0.8383218293970863,
            1.839392743096658,
            -1.4332537744963325,
            -0.3985031480144986,
            0.4893517613865405,
            9.0
        ],
        [
            -0.830034784795048,
            -0.8383218293970863,
            1.9315883006737988,
            -1.4332537744963325,
            -0.3985031480144986,
            1.164917024893623,
            10.0
        ],
        [
            -0.830034784795048,
            1.3732092889056837,
            -0.7025901786533773,
            0.802418432403741,
            -0.2157570494714138,
            1.164917024893623,
            26.0
        ],
        [
            -0.830034784795048,
            -0.8383218293970863,
            1.9277453135064209,
            -1.3965972041072783,
            -0.3985031480144986,
            1.164917024893623,
            10.0
        ]
    ],
    "ytrain": [
        [
            0.2970192986143313
        ],
        [
            -0.30377631873167527
        ],
        [
            0.6885147446767961
        ],
        [
            -1.0829857771477585
        ],
        [
            -0.09581511751856592
        ],
        [
            -0.7548105088696786
        ],
        [
            -0.39031765845885863
        ],
        [
            -0.9949852656282273
        ],
        [
            -0.3850054326001058
        ],
        [
            -0.09669249099123825
        ],
        [
            0.22636929236163922
        ],
        [
            -0.8116987932320816
        ],
        [
            0.43485662423616367
        ],
        [
            0.21571829908747644
        ],
        [
            0.46797779801364603
        ],
        [
            -1.0974079149090215
        ],
        [
            -1.152498692176904
        ],
        [
            -0.811123369852118
        ],
        [
            0.6864816513270134
        ],
        [
            -0.2434329688436304
        ],
        [
            -0.7599585245716063
        ],
        [
            -0.17304810874136198
        ],
        [
            -0.2767820691839026
        ],
        [
            -0.8168240171405295
        ],
        [
            0.08123604103925802
        ],
        [
            0.268064288820328
        ],
        [
            0.8507147872553167
        ],
        [
            -1.015706489611092
        ],
        [
            4.356942889409617
        ],
        [
            -0.630340932642228
        ],
        [
            -0.6300056954505716
        ],
        [
            -0.06053480165529655
        ],
        [
            0.21665982383725477
        ],
        [
            0.7807756067159309
        ],
        [
            0.21666410159892574
        ],
        [
            -0.059619318523269585
        ],
        [
            -0.05940494834252598
        ],
        [
            -0.05949052078307112
        ],
        [
            0.4358311402513409
        ],
        [
            0.4660430232639869
        ],
        [
            0.7807756077152761
        ],
        [
            1.7468125821521086
        ],
        [
            -0.81088570627005
        ],
        [
            1.9176225961173057
        ],
        [
            -1.2667307856333736
        ],
        [
            0.24092056735364703
        ],
        [
            -0.46558037669769914
        ],
        [
            0.21570673044486896
        ],
        [
            2.5590142649462515
        ],
        [
            -1.1075844079928234
        ],
        [
            -0.6300903363207039
        ],
        [
            -1.107584410718511
        ]
    ],
    "X_mean": [
        32.95555958754618,
        6.7581370413096,
        9.831973697496004,
        32.05420208903625,
        0.8941257869746917,
        4.826923076923077
    ],
    "X_std": [
        3.560765936184192,
        0.9043508289111895,
        13.9938957250164,
        22.36463818160925,
        2.2437107245691346,
        4.440725659022208
    ],
    "y_mean": 6.148960942909285,
    "y_std": 4.261533464487097,
    "error": null
}