{
    "clone distribution": "beta",
    "mbr_level": 7,
    "n_iterations": 15,
    "iterations": 15,
    "best_values": [
        9.628241735307812,
        9.171002340340095,
        7.167537248263866,
        9.101179018127295,
        7.8417473277004826,
        7.823924346836332,
        7.844240975017211,
        7.835789182479504,
        7.823949271045034,
        7.823927204205814,
        7.836619354544809,
        7.844885219703918,
        7.844501771671073,
        7.823915097692015,
        26.69270379890209,
        7.829252091688569,
        26.692703797885148
    ],
    "best_points": [
        [
            30.9999,
            6.399900000000001,
            0.0,
            50.0,
            0.0,
            0.0,
            3.0
        ],
        [
            30.99995,
            6.399900000000001,
            0.0,
            50.0,
            0.0,
            0.0,
            21.0
        ],
        [
            31.0,
            6.399900000000001,
            0.0,
            50.0,
            0.0,
            0.0,
            6.0
        ],
        [
            30.99995,
            6.399900000000001,
            0.0,
            50.0,
            0.0,
            0.0,
            17.0
        ],
        [
            35.0,
            7.0,
            0.0,
            0.0,
            50.0,
            7.0,
            3.0
        ],
        [
            40.0,
            6.0,
            20.0,
            10.0,
            20.0,
            7.0,
            3.0
        ],
        [
            35.0,
            7.0,
            12.5,
            12.5,
            25.0,
            7.0,
            3.0
        ],
        [
            40.0,
            7.0,
            0.0,
            0.0,
            50.0,
            7.0,
            3.0
        ],
        [
            30.0,
            8.0,
            50.0,
            0.0,
            0.0,
            7.0,
            3.0
        ],
        [
            30.0,
            8.0,
            16.666666666666664,
            0.0,
            33.33333333333333,
            7.0,
            3.0
        ],
        [
            40.0,
            7.0,
            0.0,
            50.0,
            0.0,
            7.0,
            3.0
        ],
        [
            35.0,
            7.0,
            33.33333333333333,
            16.666666666666664,
            0.0,
            7.0,
            3.0
        ],
        [
            35.0,
            7.0,
            16.666666666666664,
            16.666666666666664,
            16.666666666666664,
            7.0,
            3.0
        ],
        [
            30.0,
            6.0,
            25.0,
            0.0,
            25.0,
            7.0,
            3.0
        ],
        [
            36.75,
            7.0,
            33.333333333333336,
            16.666666666666668,
            0.0,
            10.0,
            3.0
        ],
        [
            35.0,
            7.0,
            33.87096774193549,
            16.129032258064516,
            0.0,
            10.0,
            3.0
        ],
        [
            36.75,
            7.0,
            33.333333333333336,
            16.666666666666668,
            0.0,
            10.0,
            3.0
        ]
    ],
    "batches": [
        [
            [
                30.9999,
                6.3999500000000005,
                0.0,
                50.0,
                0.0,
                0.0,
                13.0
            ],
            [
                31.0,
                6.4,
                0.0,
                50.0,
                0.0,
                0.0,
                19.0
            ],
            [
                31.0,
                6.399900000000001,
                0.0,
                50.0,
                0.0,
                0.0,
                8.0
            ],
            [
                31.0,
                6.399900000000001,
                0.0,
                50.0,
                0.0,
                0.0,
                8.0
            ],
            [
                31.0,
                6.4,
                0.0,
                50.0,
                0.0,
                0.0,
                17.0
            ],
            [
                30.99995,
                6.399900000000001,
                0.0,
                50.0,
                0.0,
                0.0,
                22.0
            ],
            [
                31.0,
                6.399900000000001,
                0.0,
                50.0,
                0.0,
                0.0,
                9.0
            ],
            [
                30.99995,
                6.3999500000000005,
                0.0,
                50.0,
                0.0,
                0.0,
                21.0
            ],
            [
                30.99995,
                6.399900000000001,
                0.0,
                50.0,
                0.0,
                0.0,
                1.0
            ],
            [
                30.9999,
                6.399900000000001,
                0.0,
                50.0,
                0.0,
                0.0,
                3.0
            ],
            [
                30.99995,
                6.399900000000001,
                0.0,
                50.0,
                0.0,
                0.0,
                25.0
            ],
            [
                30.99995,
                6.4,
                0.0,
                50.0,
                0.0,
                0.0,
                11.0
            ]
        ],
        [
            [
                30.9999,
                6.3999500000000005,
                0.0,
                50.0,
                0.0,
                0.0,
                4.0
            ],
            [
                31.0,
                6.399900000000001,
                0.0,
                50.0,
                0.0,
                0.0,
                4.0
            ],
            [
                31.0,
                6.3999500000000005,
                0.0,
                50.0,
                0.0,
                0.0,
                2.0
            ],
            [
                30.99995,
                6.399900000000001,
                0.0,
                50.0,
                0.0,
                0.0,
                21.0
            ],
            [
                31.0,
                6.4,
                0.0,
                50.0,
                0.0,
                0.0,
                12.0
            ],
            [
                30.9999,
                6.399900000000001,
                0.0,
                50.0,
                0.0,
                0.0,
                6.0
            ],
            [
                31.0,
                6.3999500000000005,
                0.0,
                50.0,
                0.0,
                0.0,
                19.0
            ],
            [
                30.9999,
                6.4,
                0.0,
                50.0,
                0.0,
                0.0,
                14.0
            ],
            [
                30.9999,
                6.4,
                0.0,
                50.0,
                0.0,
                0.0,
                2.0
            ],
            [
                31.0,
                6.4,
                0.0,
                50.0,
                0.0,
                0.0,
                27.0
            ],
            [
                30.9999,
                6.4,
                0.0,
                50.0,
                0.0,
                0.0,
                17.0
            ],
            [
                31.0,
                6.4,
                0.0,
                50.0,
                0.0,
                0.0,
                12.0
            ]
        ],
        [
            [
                30.9999,
                6.3999500000000005,
                0.0,
                50.0,
                0.0,
                0.0,
                8.0
            ],
            [
                30.99995,
                6.399900000000001,
                0.0,
                50.0,
                0.0,
                0.0,
                19.0
            ],
            [
                30.99995,
                6.3999500000000005,
                0.0,
                50.0,
                0.0,
                0.0,
                21.0
            ],
            [
                30.9999,
                6.3999500000000005,
                0.0,
                50.0,
                0.0,
                0.0,
                1.0
            ],
            [
                31.0,
                6.4,
                0.0,
                50.0,
                0.0,
                0.0,
                6.0
            ],
            [
                30.9999,
                6.4,
                0.0,
                50.0,
                0.0,
                0.0,
                10.0
            ],
            [
                31.0,
                6.399900000000001,
                0.0,
                50.0,
                0.0,
                0.0,
                24.0
            ],
            [
                30.99995,
                6.4,
                0.0,
                50.0,
                0.0,
                0.0,
                8.0
            ],
            [
                31.0,
                6.3999500000000005,
                0.0,
                50.0,
                0.0,
                0.0,
                20.0
            ],
            [
                31.0,
                6.399900000000001,
                0.0,
                50.0,
                0.0,
                0.0,
                14.0
            ],
            [
                31.0,
                6.3999500000000005,
                0.0,
                50.0,
                0.0,
                0.0,
                16.0
            ],
            [
                31.0,
                6.399900000000001,
                0.0,
                50.0,
                0.0,
                0.0,
                6.0
            ]
        ],
        [
            [
                31.0,
                6.3999500000000005,
                0.0,
                50.0,
                0.0,
                0.0,
                25.0
            ],
            [
                31.0,
                6.399900000000001,
                0.0,
                50.0,
                0.0,
                0.0,
                27.0
            ],
            [
                30.9999,
                6.4,
                0.0,
                50.0,
                0.0,
                0.0,
                20.0
            ],
            [
                31.0,
                6.3999500000000005,
                0.0,
                50.0,
                0.0,
                0.0,
                27.0
            ],
            [
                30.9999,
                6.3999500000000005,
                0.0,
                50.0,
                0.0,
                0.0,
                22.0
            ],
            [
                30.99995,
                6.399900000000001,
                0.0,
                50.0,
                0.0,
                0.0,
                22.0
            ],
            [
                30.9999,
                6.4,
                0.0,
                50.0,
                0.0,
                0.0,
                5.0
            ],
            [
                30.99995,
                6.399900000000001,
                0.0,
                50.0,
                0.0,
                0.0,
                17.0
            ],
            [
                30.99995,
                6.4,
                0.0,
                50.0,
                0.0,
                0.0,
                5.0
            ],
            [
                30.9999,
                6.3999500000000005,
                0.0,
                50.0,
                0.0,
                0.0,
                3.0
            ],
            [
                30.9999,
                6.3999500000000005,
                0.0,
                50.0,
                0.0,
                0.0,
                14.0
            ],
            [
                30.9999,
                6.3999500000000005,
                0.0,
                50.0,
                0.0,
                0.0,
                13.0
            ]
        ],
        [
            [
                40.0,
                7.0,
                0.0,
                33.33333333333333,
                16.666666666666664,
                7.0,
                3.0
            ],
            [
                30.0,
                8.0,
                25.0,
                25.0,
                0.0,
                7.0,
                3.0
            ],
            [
                40.0,
                6.0,
                25.0,
                25.0,
                0.0,
                7.0,
                3.0
            ],
            [
                35.0,
                7.0,
                0.0,
                0.0,
                50.0,
                7.0,
                3.0
            ]
        ],
        [
            [
                35.0,
                6.0,
                0.0,
                50.0,
                0.0,
                7.0,
                3.0
            ],
            [
                40.0,
                6.0,
                20.0,
                10.0,
                20.0,
                7.0,
                3.0
            ],
            [
                40.0,
                6.0,
                50.0,
                0.0,
                0.0,
                7.0,
                3.0
            ],
            [
                30.0,
                8.0,
                0.0,
                0.0,
                50.0,
                7.0,
                3.0
            ]
        ],
        [
            [
                40.0,
                6.0,
                16.666666666666664,
                33.33333333333333,
                0.0,
                7.0,
                3.0
            ],
            [
                35.0,
                6.0,
                16.666666666666664,
                0.0,
                33.33333333333333,
                7.0,
                3.0
            ],
            [
                35.0,
                8.0,
                0.0,
                50.0,
                0.0,
                7.0,
                3.0
            ],
            [
                35.0,
                7.0,
                12.5,
                12.5,
                25.0,
                7.0,
                3.0
            ]
        ],
        [
            [
                40.0,
                8.0,
                50.0,
                0.0,
                0.0,
                7.0,
                3.0
            ],
            [
                30.0,
                6.0,
                0.0,
                0.0,
                0.0,
                7.0,
                3.0
            ],
            [
                40.0,
                7.0,
                0.0,
                0.0,
                50.0,
                7.0,
                3.0
            ],
            [
                30.0,
                7.0,
                20.0,
                20.0,
                10.0,
                7.0,
                3.0
            ]
        ],
        [
            [
                35.0,
                8.0,
                25.0,
                25.0,
                0.0,
                7.0,
                3.0
            ],
            [
                35.0,
                6.0,
                0.0,
                0.0,
                50.0,
                7.0,
                3.0
            ],
            [
                30.0,
                8.0,
                50.0,
                0.0,
                0.0,
                7.0,
                3.0
            ],
            [
                40.0,
                6.0,
                0.0,
                25.0,
                25.0,
                7.0,
                3.0
            ]
        ],
        [
            [
                30.0,
                7.0,
                0.0,
                50.0,
                0.0,
                7.0,
                3.0
            ],
            [
                30.0,
                8.0,
                16.666666666666664,
                0.0,
                33.33333333333333,
                7.0,
                3.0
            ],
            [
                30.0,
                8.0,
                10.0,
                20.0,
                20.0,
                7.0,
                3.0
            ],
            [
                40.0,
                6.0,
                33.33333333333333,
                0.0,
                16.666666666666664,
                7.0,
                3.0
            ]
        ],
        [
            [
                35.0,
                6.0,
                12.5,
                25.0,
                12.5,
                7.0,
                3.0
            ],
            [
                30.0,
                6.0,
                12.5,
                12.5,
                25.0,
                7.0,
                3.0
            ],
            [
                40.0,
                7.0,
                0.0,
                50.0,
                0.0,
                7.0,
                3.0
            ],
            [
                35.0,
                6.0,
                20.0,
                10.0,
                20.0,
                7.0,
                3.0
            ]
        ],
        [
            [
                40.0,
                8.0,
                20.0,
                10.0,
                20.0,
                7.0,
                3.0
            ],
            [
                40.0,
                6.0,
                16.666666666666664,
                16.666666666666664,
                16.666666666666664,
                7.0,
                3.0
            ],
            [
                35.0,
                6.0,
                10.0,
                20.0,
                20.0,
                7.0,
                3.0
            ],
            [
                35.0,
                7.0,
                33.33333333333333,
                16.666666666666664,
                0.0,
                7.0,
                3.0
            ]
        ],
        [
            [
                40.0,
                7.0,
                16.666666666666664,
                16.666666666666664,
                16.666666666666664,
                7.0,
                3.0
            ],
            [
                40.0,
                8.0,
                0.0,
                33.33333333333333,
                16.666666666666664,
                7.0,
                3.0
            ],
            [
                40.0,
                7.0,
                0.0,
                25.0,
                25.0,
                7.0,
                3.0
            ],
            [
                35.0,
                7.0,
                16.666666666666664,
                16.666666666666664,
                16.666666666666664,
                7.0,
                3.0
            ]
        ],
        [
            [
                40.0,
                6.0,
                16.666666666666664,
                0.0,
                33.33333333333333,
                7.0,
                3.0
            ],
            [
                30.0,
                6.0,
                25.0,
                0.0,
                25.0,
                7.0,
                3.0
            ],
            [
                35.0,
                8.0,
                16.666666666666664,
                33.33333333333333,
                0.0,
                7.0,
                3.0
            ],
            [
                30.0,
                8.0,
                0.0,
                0.0,
                50.0,
                7.0,
                3.0
            ]
        ],
        [
            [
                36.75,
                7.0,
                33.333333333333336,
                16.666666666666668,
                0.0,
                10.0,
                3.0
            ]
        ],
        [
            [
                35.0,
                7.0,
                33.87096774193549,
                16.129032258064516,
                0.0,
                10.0,
                3.0
            ]
        ],
        [
            [
                36.75,
                7.0,
                33.333333333333336,
                16.666666666666668,
                0.0,
                10.0,
                3.0
            ]
        ]
    ],
    "cumulative_cost_list": [
        0,
        120,
        240,
        360,
        480,
        2780,
        5080,
        7380,
        9680,
        11980,
        14280,
        16580,
        18880,
        21180,
        23480,
        25580,
        27680,
        29780
    ],
    "fidelities": [
        0,
        0,
        0,
        0,
        7,
        7,
        7,
        7,
        7,
        7,
        7,
        7,
        7,
        7,
        10,
        10,
        10
    ],
    "clones": [
        13.0,
        19.0,
        8.0,
        8.0,
        17.0,
        22.0,
        9.0,
        21.0,
        1.0,
        3.0,
        25.0,
        11.0,
        4.0,
        4.0,
        2.0,
        21.0,
        12.0,
        6.0,
        19.0,
        14.0,
        2.0,
        27.0,
        17.0,
        12.0,
        8.0,
        19.0,
        21.0,
        1.0,
        6.0,
        10.0,
        24.0,
        8.0,
        20.0,
        14.0,
        16.0,
        6.0,
        25.0,
        27.0,
        20.0,
        27.0,
        22.0,
        22.0,
        5.0,
        17.0,
        5.0,
        3.0,
        14.0,
        13.0
    ],
    "X_mean": 0,
    "X_std": 1,
    "y_mean": 0,
    "y_std": 1,
    "error": null
}